{
"meta":{"test_sets":[],"test_metrics":[],"learn_metrics":[{"best_value":"Min","name":"Logloss"}],"launch_mode":"Train","parameters":"","iteration_count":1000,"learn_sets":["learn"],"name":"experiment"},
"iterations":[
{"learn":[0.6892193604],"iteration":0,"passed_time":0.005190020852,"remaining_time":5.184830831},
{"learn":[0.6852462769],"iteration":1,"passed_time":0.02042531876,"remaining_time":10.19223406},
{"learn":[0.6815773773],"iteration":2,"passed_time":0.03442724003,"remaining_time":11.44131944},
{"learn":[0.6775039673],"iteration":3,"passed_time":0.04403491263,"remaining_time":10.96469324},
{"learn":[0.6735289001],"iteration":4,"passed_time":0.05141072201,"remaining_time":10.23073368},
{"learn":[0.6700968933],"iteration":5,"passed_time":0.05992248293,"remaining_time":9.927158005},
{"learn":[0.6667721558],"iteration":6,"passed_time":0.06784565624,"remaining_time":9.624390949},
{"learn":[0.6631668854],"iteration":7,"passed_time":0.07623573477,"remaining_time":9.453231111},
{"learn":[0.6602274323],"iteration":8,"passed_time":0.08113937061,"remaining_time":8.934346253},
{"learn":[0.6568344116],"iteration":9,"passed_time":0.0870886225,"remaining_time":8.621773628},
{"learn":[0.6537174988],"iteration":10,"passed_time":0.09553103064,"remaining_time":8.589108119},
{"learn":[0.6506285095],"iteration":11,"passed_time":0.1036662768,"remaining_time":8.535190121},
{"learn":[0.6480197144],"iteration":12,"passed_time":0.1121496339,"remaining_time":8.514745284},
{"learn":[0.6449017334],"iteration":13,"passed_time":0.1201060934,"remaining_time":8.458900575},
{"learn":[0.6419190979],"iteration":14,"passed_time":0.1284518705,"remaining_time":8.435006164},
{"learn":[0.6387530136],"iteration":15,"passed_time":0.1341410862,"remaining_time":8.2496768},
{"learn":[0.6359056854],"iteration":16,"passed_time":0.1450929202,"remaining_time":8.389784737},
{"learn":[0.6329712677],"iteration":17,"passed_time":0.1512499133,"remaining_time":8.251523049},
{"learn":[0.6299514771],"iteration":18,"passed_time":0.1606371774,"remaining_time":8.293951105},
{"learn":[0.6268577576],"iteration":19,"passed_time":0.1744911925,"remaining_time":8.55006843},
{"learn":[0.6241407776],"iteration":20,"passed_time":0.1883975276,"remaining_time":8.782913309},
{"learn":[0.6213977051],"iteration":21,"passed_time":0.1940137653,"remaining_time":8.624793747},
{"learn":[0.619599762],"iteration":22,"passed_time":0.1976311253,"remaining_time":8.395026495},
{"learn":[0.6171274948],"iteration":23,"passed_time":0.2043140808,"remaining_time":8.30877262},
{"learn":[0.6145508575],"iteration":24,"passed_time":0.2087871159,"remaining_time":8.14269752},
{"learn":[0.6116580582],"iteration":25,"passed_time":0.2239893707,"remaining_time":8.390986424},
{"learn":[0.6088637543],"iteration":26,"passed_time":0.2399417192,"remaining_time":8.646788622},
{"learn":[0.6061695862],"iteration":27,"passed_time":0.2507705244,"remaining_time":8.705319634},
{"learn":[0.6038209534],"iteration":28,"passed_time":0.2588984413,"remaining_time":8.668634018},
{"learn":[0.6012820816],"iteration":29,"passed_time":0.2720063446,"remaining_time":8.79487181},
{"learn":[0.5994301224],"iteration":30,"passed_time":0.2856833692,"remaining_time":8.929909185},
{"learn":[0.5972600555],"iteration":31,"passed_time":0.2904763626,"remaining_time":8.786909969},
{"learn":[0.5951343918],"iteration":32,"passed_time":0.2993303652,"remaining_time":8.771286763},
{"learn":[0.5928334808],"iteration":33,"passed_time":0.3040324974,"remaining_time":8.63809978},
{"learn":[0.5911651993],"iteration":34,"passed_time":0.3146147425,"remaining_time":8.674377901},
{"learn":[0.5891704559],"iteration":35,"passed_time":0.3248506964,"remaining_time":8.69877976},
{"learn":[0.5869497299],"iteration":36,"passed_time":0.3382295583,"remaining_time":8.803109855},
{"learn":[0.5845496368],"iteration":37,"passed_time":0.3564587668,"remaining_time":9.024035096},
{"learn":[0.5824686813],"iteration":38,"passed_time":0.3686381203,"remaining_time":9.083621374},
{"learn":[0.5806341553],"iteration":39,"passed_time":0.3822632292,"remaining_time":9.174317502},
{"learn":[0.5788783264],"iteration":40,"passed_time":0.4346915787,"remaining_time":10.16754205},
{"learn":[0.5768632507],"iteration":41,"passed_time":0.4481770139,"remaining_time":10.22270427},
{"learn":[0.5746741486],"iteration":42,"passed_time":0.4555323368,"remaining_time":10.13824294},
{"learn":[0.5728091049],"iteration":43,"passed_time":0.4791582563,"remaining_time":10.41080211},
{"learn":[0.571222496],"iteration":44,"passed_time":0.485300876,"remaining_time":10.29916303},
{"learn":[0.5692245483],"iteration":45,"passed_time":0.5317728043,"remaining_time":11.02850555},
{"learn":[0.5671528625],"iteration":46,"passed_time":0.5405148033,"remaining_time":10.95980016},
{"learn":[0.5658788681],"iteration":47,"passed_time":0.5541442283,"remaining_time":10.9905272},
{"learn":[0.5647030258],"iteration":48,"passed_time":0.5619428263,"remaining_time":10.90627812},
{"learn":[0.5628903961],"iteration":49,"passed_time":0.5710747916,"remaining_time":10.85042104},
{"learn":[0.5609584045],"iteration":50,"passed_time":0.6344693787,"remaining_time":11.80610667},
{"learn":[0.558823204],"iteration":51,"passed_time":0.6463009744,"remaining_time":11.78256392},
{"learn":[0.557327652],"iteration":52,"passed_time":0.6533231935,"remaining_time":11.67352951},
{"learn":[0.5558571243],"iteration":53,"passed_time":0.6632868144,"remaining_time":11.61980234},
{"learn":[0.5543162918],"iteration":54,"passed_time":0.703521776,"remaining_time":12.08778324},
{"learn":[0.5524458313],"iteration":55,"passed_time":0.7181996415,"remaining_time":12.10679396},
{"learn":[0.5509208679],"iteration":56,"passed_time":0.7279135107,"remaining_time":12.04249896},
{"learn":[0.549274826],"iteration":57,"passed_time":0.7402520042,"remaining_time":12.02271359},
{"learn":[0.5473394012],"iteration":58,"passed_time":0.7459243844,"remaining_time":11.89686179},
{"learn":[0.5465372849],"iteration":59,"passed_time":0.747968247,"remaining_time":11.7181692},
{"learn":[0.5450730133],"iteration":60,"passed_time":0.7807987462,"remaining_time":12.0191807},
{"learn":[0.5434753036],"iteration":61,"passed_time":0.7907141452,"remaining_time":11.96273981},
{"learn":[0.5419186401],"iteration":62,"passed_time":0.7945687323,"remaining_time":11.81763337},
{"learn":[0.5411557007],"iteration":63,"passed_time":0.7976068521,"remaining_time":11.66500021},
{"learn":[0.5392737579],"iteration":64,"passed_time":0.8012539412,"remaining_time":11.52572977},
{"learn":[0.5376461792],"iteration":65,"passed_time":0.8090305168,"remaining_time":11.44900762},
{"learn":[0.5363540649],"iteration":66,"passed_time":0.8133845836,"remaining_time":11.32668383},
{"learn":[0.5351026535],"iteration":67,"passed_time":0.8179421804,"remaining_time":11.2106193},
{"learn":[0.5338214111],"iteration":68,"passed_time":0.8255736801,"remaining_time":11.13926226},
{"learn":[0.5329770279],"iteration":69,"passed_time":0.8311478458,"remaining_time":11.04239281},
{"learn":[0.5315585709],"iteration":70,"passed_time":0.8378918564,"remaining_time":10.9634019},
{"learn":[0.5302839661],"iteration":71,"passed_time":0.8430047786,"remaining_time":10.86539492},
{"learn":[0.5292131424],"iteration":72,"passed_time":0.846680089,"remaining_time":10.75167729},
{"learn":[0.5281123352],"iteration":73,"passed_time":0.8503977826,"remaining_time":10.64146414},
{"learn":[0.5268343353],"iteration":74,"passed_time":0.8578154125,"remaining_time":10.57972342},
{"learn":[0.5253375244],"iteration":75,"passed_time":0.8615229746,"remaining_time":10.47430564},
{"learn":[0.5238422394],"iteration":76,"passed_time":0.8654197619,"remaining_time":10.37379793},
{"learn":[0.523373642],"iteration":77,"passed_time":0.8706151872,"remaining_time":10.29111798},
{"learn":[0.5220026398],"iteration":78,"passed_time":0.874332654,"remaining_time":10.1931693},
{"learn":[0.5211643219],"iteration":79,"passed_time":0.8779473595,"remaining_time":10.09639463},
{"learn":[0.520112381],"iteration":80,"passed_time":0.8808996623,"remaining_time":9.99440481},
{"learn":[0.5190300369],"iteration":81,"passed_time":0.8876271894,"remaining_time":9.937094633},
{"learn":[0.5178100586],"iteration":82,"passed_time":0.8915431228,"remaining_time":9.849940284},
{"learn":[0.5168761444],"iteration":83,"passed_time":0.8952510218,"remaining_time":9.762499238},
{"learn":[0.5158670807],"iteration":84,"passed_time":0.9010221753,"remaining_time":9.69923871},
{"learn":[0.514549675],"iteration":85,"passed_time":0.9061036326,"remaining_time":9.629985119},
{"learn":[0.5134189606],"iteration":86,"passed_time":0.9097863951,"remaining_time":9.547528491},
{"learn":[0.512143631],"iteration":87,"passed_time":0.9133998596,"remaining_time":9.466144},
{"learn":[0.5113122559],"iteration":88,"passed_time":0.9211524308,"remaining_time":9.428874882},
{"learn":[0.509932785],"iteration":89,"passed_time":0.9247629136,"remaining_time":9.35038057},
{"learn":[0.5086763763],"iteration":90,"passed_time":0.9286145527,"remaining_time":9.275940972},
{"learn":[0.5074645615],"iteration":91,"passed_time":0.9361968226,"remaining_time":9.239855597},
{"learn":[0.5067765045],"iteration":92,"passed_time":0.9407520388,"remaining_time":9.174861282},
{"learn":[0.505938797],"iteration":93,"passed_time":0.9442953149,"remaining_time":9.101399524},
{"learn":[0.5052565002],"iteration":94,"passed_time":0.9522482018,"remaining_time":9.071417081},
{"learn":[0.5043482971],"iteration":95,"passed_time":0.9559414033,"remaining_time":9.001781547},
{"learn":[0.5032947922],"iteration":96,"passed_time":0.9596453597,"remaining_time":8.933605771},
{"learn":[0.5025174713],"iteration":97,"passed_time":0.9656484111,"remaining_time":8.887906804},
{"learn":[0.5013593292],"iteration":98,"passed_time":0.9700939633,"remaining_time":8.828834959},
{"learn":[0.4999660492],"iteration":99,"passed_time":0.9737109974,"remaining_time":8.763398977},
{"learn":[0.498642807],"iteration":100,"passed_time":0.9777685079,"remaining_time":8.703107808},
{"learn":[0.4973946381],"iteration":101,"passed_time":0.9841006424,"remaining_time":8.663944871},
{"learn":[0.4963248444],"iteration":102,"passed_time":0.9878067116,"remaining_time":8.602549712},
{"learn":[0.4956444931],"iteration":103,"passed_time":0.9913727459,"remaining_time":8.541057503},
{"learn":[0.4945969391],"iteration":104,"passed_time":0.9971596355,"remaining_time":8.499598798},
{"learn":[0.493759346],"iteration":105,"passed_time":1.001861525,"remaining_time":8.449662297},
{"learn":[0.4927619553],"iteration":106,"passed_time":1.005538866,"remaining_time":8.392020628},
{"learn":[0.4919498062],"iteration":107,"passed_time":1.009288215,"remaining_time":8.335973034},
{"learn":[0.4909813309],"iteration":108,"passed_time":1.016600438,"remaining_time":8.310009087},
{"learn":[0.4901581955],"iteration":109,"passed_time":1.020380264,"remaining_time":8.255803958},
{"learn":[0.4892796326],"iteration":110,"passed_time":1.02417527,"remaining_time":8.202628968},
{"learn":[0.4885347748],"iteration":111,"passed_time":1.031127694,"remaining_time":8.175369577},
{"learn":[0.487662735],"iteration":112,"passed_time":1.035678912,"remaining_time":8.129621197},
{"learn":[0.4867472076],"iteration":113,"passed_time":1.03939725,"remaining_time":8.07812249},
{"learn":[0.4858683014],"iteration":114,"passed_time":1.047586915,"remaining_time":8.061864523},
{"learn":[0.4850967407],"iteration":115,"passed_time":1.051540367,"remaining_time":8.013462796},
{"learn":[0.4841764832],"iteration":116,"passed_time":1.05521967,"remaining_time":7.963751869},
{"learn":[0.4834703445],"iteration":117,"passed_time":1.062103941,"remaining_time":7.938776917},
{"learn":[0.4826870728],"iteration":118,"passed_time":1.066263688,"remaining_time":7.893935372},
{"learn":[0.4817565918],"iteration":119,"passed_time":1.069829073,"remaining_time":7.8454132},
{"learn":[0.4809578705],"iteration":120,"passed_time":1.073315901,"remaining_time":7.797063449},
{"learn":[0.480120163],"iteration":121,"passed_time":1.083112941,"remaining_time":7.794861985},
{"learn":[0.4790879059],"iteration":122,"passed_time":1.08684008,"remaining_time":7.749258128},
{"learn":[0.478377533],"iteration":123,"passed_time":1.092488075,"remaining_time":7.717899626},
{"learn":[0.477483139],"iteration":124,"passed_time":1.098123017,"remaining_time":7.686861116},
{"learn":[0.4769365692],"iteration":125,"passed_time":1.102387219,"remaining_time":7.646717697},
{"learn":[0.4762443542],"iteration":126,"passed_time":1.111065919,"remaining_time":7.637484624},
{"learn":[0.4755467987],"iteration":127,"passed_time":1.114861941,"remaining_time":7.594996974},
{"learn":[0.4748209],"iteration":128,"passed_time":1.118779898,"remaining_time":7.553932488},
{"learn":[0.4736897659],"iteration":129,"passed_time":1.125325819,"remaining_time":7.531026634},
{"learn":[0.4729456329],"iteration":130,"passed_time":1.130973832,"remaining_time":7.502414201},
{"learn":[0.4721710587],"iteration":131,"passed_time":1.134648556,"remaining_time":7.461173839},
{"learn":[0.4714377594],"iteration":132,"passed_time":1.141018021,"remaining_time":7.438064841},
{"learn":[0.4703518677],"iteration":133,"passed_time":1.145640271,"remaining_time":7.403913993},
{"learn":[0.4698420715],"iteration":134,"passed_time":1.14928789,"remaining_time":7.363955737},
{"learn":[0.4692269516],"iteration":135,"passed_time":1.152968775,"remaining_time":7.324742807},
{"learn":[0.4685645294],"iteration":136,"passed_time":1.160479093,"remaining_time":7.310171224},
{"learn":[0.4677936554],"iteration":137,"passed_time":1.165789741,"remaining_time":7.281962004},
{"learn":[0.4671405029],"iteration":138,"passed_time":1.169927686,"remaining_time":7.246818257},
{"learn":[0.4670072937],"iteration":139,"passed_time":1.173039238,"remaining_time":7.20581246},
{"learn":[0.4662674332],"iteration":140,"passed_time":1.17653391,"remaining_time":7.167678217},
{"learn":[0.4654437256],"iteration":141,"passed_time":1.18018841,"remaining_time":7.130997579},
{"learn":[0.4648691559],"iteration":142,"passed_time":1.184092317,"remaining_time":7.096273534},
{"learn":[0.4642045212],"iteration":143,"passed_time":1.189851218,"remaining_time":7.073004462},
{"learn":[0.463265152],"iteration":144,"passed_time":1.193961351,"remaining_time":7.040254864},
{"learn":[0.4625347137],"iteration":145,"passed_time":1.198653191,"remaining_time":7.011300174},
{"learn":[0.4620480347],"iteration":146,"passed_time":1.205640582,"remaining_time":6.99599603},
{"learn":[0.4614089966],"iteration":147,"passed_time":1.209471481,"remaining_time":6.962633122},
{"learn":[0.4608927917],"iteration":148,"passed_time":1.213167988,"remaining_time":6.928899043},
{"learn":[0.4603554153],"iteration":149,"passed_time":1.220582639,"remaining_time":6.916634952},
{"learn":[0.4595558929],"iteration":150,"passed_time":1.224329099,"remaining_time":6.883810632},
{"learn":[0.4587935257],"iteration":151,"passed_time":1.228007137,"remaining_time":6.850987183},
{"learn":[0.4582543945],"iteration":152,"passed_time":1.231753283,"remaining_time":6.818921771},
{"learn":[0.457638092],"iteration":153,"passed_time":1.238117725,"remaining_time":6.801607762},
{"learn":[0.4567857361],"iteration":154,"passed_time":1.242794318,"remaining_time":6.775233542},
{"learn":[0.4561374664],"iteration":155,"passed_time":1.24662954,"remaining_time":6.744585462},
{"learn":[0.4553054047],"iteration":156,"passed_time":1.253009651,"remaining_time":6.727943541},
{"learn":[0.4546812439],"iteration":157,"passed_time":1.256898379,"remaining_time":6.698154654},
{"learn":[0.4540463257],"iteration":158,"passed_time":1.261480422,"remaining_time":6.672358709},
{"learn":[0.4534272766],"iteration":159,"passed_time":1.267957357,"remaining_time":6.656776122},
{"learn":[0.4525494385],"iteration":160,"passed_time":1.271668089,"remaining_time":6.626891471},
{"learn":[0.4518371582],"iteration":161,"passed_time":1.275280499,"remaining_time":6.596821345},
{"learn":[0.4512062073],"iteration":162,"passed_time":1.279004064,"remaining_time":6.567646634},
{"learn":[0.4505376434],"iteration":163,"passed_time":1.285924868,"remaining_time":6.555080425},
{"learn":[0.4499081421],"iteration":164,"passed_time":1.289765068,"remaining_time":6.526992918},
{"learn":[0.4491452026],"iteration":165,"passed_time":1.293322677,"remaining_time":6.497777785},
{"learn":[0.448690567],"iteration":166,"passed_time":1.299772417,"remaining_time":6.483295948},
{"learn":[0.4479307556],"iteration":167,"passed_time":1.30364671,"remaining_time":6.456155137},
{"learn":[0.4474411011],"iteration":168,"passed_time":1.307273491,"remaining_time":6.428072608},
{"learn":[0.4469114304],"iteration":169,"passed_time":1.310978149,"remaining_time":6.400658022},
{"learn":[0.4463497162],"iteration":170,"passed_time":1.316408108,"remaining_time":6.381884923},
{"learn":[0.4460061646],"iteration":171,"passed_time":1.320198632,"remaining_time":6.35537481},
{"learn":[0.4454934311],"iteration":172,"passed_time":1.323798137,"remaining_time":6.328214214},
{"learn":[0.4450075531],"iteration":173,"passed_time":1.329514228,"remaining_time":6.311372141},
{"learn":[0.4443271637],"iteration":174,"passed_time":1.335829809,"remaining_time":6.297483383},
{"learn":[0.443738327],"iteration":175,"passed_time":1.339492082,"remaining_time":6.271258383},
{"learn":[0.4431447601],"iteration":176,"passed_time":1.347325647,"remaining_time":6.26468366},
{"learn":[0.442650528],"iteration":177,"passed_time":1.35395898,"remaining_time":6.252552144},
{"learn":[0.4422600555],"iteration":178,"passed_time":1.358313853,"remaining_time":6.230031693},
{"learn":[0.4418391037],"iteration":179,"passed_time":1.365414807,"remaining_time":6.220223009},
{"learn":[0.4412725067],"iteration":180,"passed_time":1.369650632,"remaining_time":6.197479933},
{"learn":[0.4407564163],"iteration":181,"passed_time":1.373923899,"remaining_time":6.175108511},
{"learn":[0.4399486542],"iteration":182,"passed_time":1.380773699,"remaining_time":6.16443777},
{"learn":[0.4393072128],"iteration":183,"passed_time":1.385118867,"remaining_time":6.142701061},
{"learn":[0.4387521362],"iteration":184,"passed_time":1.388931105,"remaining_time":6.118804599},
{"learn":[0.4382363892],"iteration":185,"passed_time":1.395342257,"remaining_time":6.106497834},
{"learn":[0.437700119],"iteration":186,"passed_time":1.399114671,"remaining_time":6.082781965},
{"learn":[0.4373157501],"iteration":187,"passed_time":1.402803175,"remaining_time":6.058915842},
{"learn":[0.4369696808],"iteration":188,"passed_time":1.406592822,"remaining_time":6.035697243},
{"learn":[0.4366227722],"iteration":189,"passed_time":1.411874445,"remaining_time":6.019043688},
{"learn":[0.4359520721],"iteration":190,"passed_time":1.415552202,"remaining_time":5.995715871},
{"learn":[0.4353604126],"iteration":191,"passed_time":1.419270143,"remaining_time":5.97276185},
{"learn":[0.4348046875],"iteration":192,"passed_time":1.424617751,"remaining_time":5.956821375},
{"learn":[0.4343144989],"iteration":193,"passed_time":1.429805241,"remaining_time":5.940324868},
{"learn":[0.4336461639],"iteration":194,"passed_time":1.433455087,"remaining_time":5.917596643},
{"learn":[0.4332023621],"iteration":195,"passed_time":1.437260964,"remaining_time":5.895703138},
{"learn":[0.4327453613],"iteration":196,"passed_time":1.444267632,"remaining_time":5.887040144},
{"learn":[0.432309227],"iteration":197,"passed_time":1.449667415,"remaining_time":5.871885186},
{"learn":[0.4316810608],"iteration":198,"passed_time":1.453441045,"remaining_time":5.850282797},
{"learn":[0.4310994339],"iteration":199,"passed_time":1.460036422,"remaining_time":5.840145686},
{"learn":[0.4306896591],"iteration":200,"passed_time":1.463981241,"remaining_time":5.81950752},
{"learn":[0.4300610352],"iteration":201,"passed_time":1.467915381,"remaining_time":5.798992445},
{"learn":[0.4297370148],"iteration":202,"passed_time":1.47547874,"remaining_time":5.792889439},
{"learn":[0.4292776871],"iteration":203,"passed_time":1.479365788,"remaining_time":5.772427292},
{"learn":[0.4289342499],"iteration":204,"passed_time":1.482951608,"remaining_time":5.750958675},
{"learn":[0.4282098389],"iteration":205,"passed_time":1.488153659,"remaining_time":5.735893228},
{"learn":[0.4279471207],"iteration":206,"passed_time":1.494222371,"remaining_time":5.724243188},
{"learn":[0.4274041748],"iteration":207,"passed_time":1.498803937,"remaining_time":5.706984222},
{"learn":[0.4268406296],"iteration":208,"passed_time":1.505338641,"remaining_time":5.697238587},
{"learn":[0.4264760971],"iteration":209,"passed_time":1.509945832,"remaining_time":5.680272416},
{"learn":[0.4259664917],"iteration":210,"passed_time":1.514519204,"remaining_time":5.663296929},
{"learn":[0.4255167007],"iteration":211,"passed_time":1.526397878,"remaining_time":5.673592114},
{"learn":[0.4253398514],"iteration":212,"passed_time":1.530545219,"remaining_time":5.655113086},
{"learn":[0.4249069214],"iteration":213,"passed_time":1.539751954,"remaining_time":5.655350633},
{"learn":[0.4243753052],"iteration":214,"passed_time":1.544512329,"remaining_time":5.639265945},
{"learn":[0.4238735199],"iteration":215,"passed_time":1.549494993,"remaining_time":5.624092938},
{"learn":[0.4234631348],"iteration":216,"passed_time":1.558800293,"remaining_time":5.624611197},
{"learn":[0.4233197784],"iteration":217,"passed_time":1.561700805,"remaining_time":5.602064355},
{"learn":[0.4228833389],"iteration":218,"passed_time":1.566009385,"remaining_time":5.584718402},
{"learn":[0.4223722458],"iteration":219,"passed_time":1.573073831,"remaining_time":5.577261766},
{"learn":[0.4218856049],"iteration":220,"passed_time":1.57682015,"remaining_time":5.558112657},
{"learn":[0.42140625],"iteration":221,"passed_time":1.58436131,"remaining_time":5.552401348},
{"learn":[0.4208689117],"iteration":222,"passed_time":1.590791752,"remaining_time":5.542803549},
{"learn":[0.420436554],"iteration":223,"passed_time":1.594443754,"remaining_time":5.523608718},
{"learn":[0.4201622391],"iteration":224,"passed_time":1.601256704,"remaining_time":5.515439758},
{"learn":[0.4195906448],"iteration":225,"passed_time":1.605036607,"remaining_time":5.496895281},
{"learn":[0.4193481445],"iteration":226,"passed_time":1.608555557,"remaining_time":5.47759227},
{"learn":[0.4188265228],"iteration":227,"passed_time":1.615971033,"remaining_time":5.471621216},
{"learn":[0.4183120346],"iteration":228,"passed_time":1.623413931,"remaining_time":5.465729872},
{"learn":[0.4177381897],"iteration":229,"passed_time":1.628703427,"remaining_time":5.452615822},
{"learn":[0.4172114182],"iteration":230,"passed_time":1.63620735,"remaining_time":5.446941351},
{"learn":[0.4167958069],"iteration":231,"passed_time":1.640820333,"remaining_time":5.431681101},
{"learn":[0.4164118195],"iteration":232,"passed_time":1.651457638,"remaining_time":5.436343383},
{"learn":[0.4159218597],"iteration":233,"passed_time":1.658607732,"remaining_time":5.429459498},
{"learn":[0.4155522156],"iteration":234,"passed_time":1.664811352,"remaining_time":5.419492273},
{"learn":[0.4150844574],"iteration":235,"passed_time":1.672409277,"remaining_time":5.414070711},
{"learn":[0.4145858765],"iteration":236,"passed_time":1.676124405,"remaining_time":5.396130467},
{"learn":[0.4142646027],"iteration":237,"passed_time":1.68524395,"remaining_time":5.395612982},
{"learn":[0.4137347794],"iteration":238,"passed_time":1.688940634,"remaining_time":5.377756579},
{"learn":[0.4134407806],"iteration":239,"passed_time":1.692471492,"remaining_time":5.359493056},
{"learn":[0.412891922],"iteration":240,"passed_time":1.700651453,"remaining_time":5.355993581},
{"learn":[0.4126098633],"iteration":241,"passed_time":1.704912993,"remaining_time":5.340182019},
{"learn":[0.4122441483],"iteration":242,"passed_time":1.708464513,"remaining_time":5.322253646},
{"learn":[0.4119213867],"iteration":243,"passed_time":1.717248438,"remaining_time":5.320654995},
{"learn":[0.4115789032],"iteration":244,"passed_time":1.720796983,"remaining_time":5.302864174},
{"learn":[0.411231575],"iteration":245,"passed_time":1.724423823,"remaining_time":5.285429117},
{"learn":[0.4108941269],"iteration":246,"passed_time":1.732974727,"remaining_time":5.283117285},
{"learn":[0.4106772995],"iteration":247,"passed_time":1.735980306,"remaining_time":5.263940284},
{"learn":[0.4102626038],"iteration":248,"passed_time":1.739476619,"remaining_time":5.246373257},
{"learn":[0.4098212433],"iteration":249,"passed_time":1.749697547,"remaining_time":5.249092642},
{"learn":[0.4095340347],"iteration":250,"passed_time":1.754225807,"remaining_time":5.234721631},
{"learn":[0.4090961075],"iteration":251,"passed_time":1.760371169,"remaining_time":5.225228709},
{"learn":[0.4085468292],"iteration":252,"passed_time":1.766982471,"remaining_time":5.217137969},
{"learn":[0.4081214142],"iteration":253,"passed_time":1.771530765,"remaining_time":5.202999806},
{"learn":[0.4077142715],"iteration":254,"passed_time":1.788930505,"remaining_time":5.226483241},
{"learn":[0.4073201752],"iteration":255,"passed_time":1.799097389,"remaining_time":5.228626787},
{"learn":[0.4069285583],"iteration":256,"passed_time":1.802884427,"remaining_time":5.212230075},
{"learn":[0.4065351868],"iteration":257,"passed_time":1.809821457,"remaining_time":5.204990393},
{"learn":[0.4062724304],"iteration":258,"passed_time":1.815208505,"remaining_time":5.193318542},
{"learn":[0.4059586334],"iteration":259,"passed_time":1.81903641,"remaining_time":5.177257474},
{"learn":[0.4057262039],"iteration":260,"passed_time":1.825868432,"remaining_time":5.169796059},
{"learn":[0.405437088],"iteration":261,"passed_time":1.830336876,"remaining_time":5.155681734},
{"learn":[0.4053422546],"iteration":262,"passed_time":1.833373038,"remaining_time":5.137627106},
{"learn":[0.4050313568],"iteration":263,"passed_time":1.837152251,"remaining_time":5.121757789},
{"learn":[0.4047357941],"iteration":264,"passed_time":1.848079834,"remaining_time":5.125806333},
{"learn":[0.4044112778],"iteration":265,"passed_time":1.85221606,"remaining_time":5.11100221},
{"learn":[0.4039573669],"iteration":266,"passed_time":1.859856581,"remaining_time":5.105898403},
{"learn":[0.4036286926],"iteration":267,"passed_time":1.863599808,"remaining_time":5.09013082},
{"learn":[0.4032225037],"iteration":268,"passed_time":1.867286096,"remaining_time":5.074297905},
{"learn":[0.4029585266],"iteration":269,"passed_time":1.873621817,"remaining_time":5.065718245},
{"learn":[0.4026203156],"iteration":270,"passed_time":1.878558778,"remaining_time":5.053392431},
{"learn":[0.4022045135],"iteration":271,"passed_time":1.882242708,"remaining_time":5.037767249},
{"learn":[0.4017726898],"iteration":272,"passed_time":1.88630093,"remaining_time":5.023226285},
{"learn":[0.4014451218],"iteration":273,"passed_time":1.894104712,"remaining_time":5.018686206},
{"learn":[0.4010017776],"iteration":274,"passed_time":1.897882836,"remaining_time":5.003509294},
{"learn":[0.4007064819],"iteration":275,"passed_time":1.901506519,"remaining_time":4.988009855},
{"learn":[0.4003735733],"iteration":276,"passed_time":1.909799457,"remaining_time":4.98478342},
{"learn":[0.3999844742],"iteration":277,"passed_time":1.914061946,"remaining_time":4.971052968},
{"learn":[0.3997264099],"iteration":278,"passed_time":1.917689097,"remaining_time":4.955748525},
{"learn":[0.3992844009],"iteration":279,"passed_time":1.926217054,"remaining_time":4.953129568},
{"learn":[0.3987031174],"iteration":280,"passed_time":1.929810922,"remaining_time":4.937843604},
{"learn":[0.3984055328],"iteration":281,"passed_time":1.933521552,"remaining_time":4.922937853},
{"learn":[0.398073349],"iteration":282,"passed_time":1.942242739,"remaining_time":4.920805808},
{"learn":[0.3976348495],"iteration":283,"passed_time":1.94665538,"remaining_time":4.907764971},
{"learn":[0.3973929596],"iteration":284,"passed_time":1.958853708,"remaining_time":4.914317197},
{"learn":[0.3971446228],"iteration":285,"passed_time":1.96517787,"remaining_time":4.906073424},
{"learn":[0.3966687012],"iteration":286,"passed_time":1.975257432,"remaining_time":4.907172645},
{"learn":[0.3963808823],"iteration":287,"passed_time":1.979036768,"remaining_time":4.892618678},
{"learn":[0.3959849548],"iteration":288,"passed_time":1.98343264,"remaining_time":4.87965608},
{"learn":[0.3956537247],"iteration":289,"passed_time":1.989477149,"remaining_time":4.870788883},
{"learn":[0.3952713013],"iteration":290,"passed_time":1.993221137,"remaining_time":4.856336034},
{"learn":[0.3948440552],"iteration":291,"passed_time":1.996862041,"remaining_time":4.841706592},
{"learn":[0.39454216],"iteration":292,"passed_time":2.005240029,"remaining_time":4.838582597},
{"learn":[0.3941329575],"iteration":293,"passed_time":2.009029228,"remaining_time":4.824403521},
{"learn":[0.3936908722],"iteration":294,"passed_time":2.012647084,"remaining_time":4.809885405},
{"learn":[0.3933635712],"iteration":295,"passed_time":2.020371962,"remaining_time":4.80520899},
{"learn":[0.3928791809],"iteration":296,"passed_time":2.024115762,"remaining_time":4.791088823},
{"learn":[0.3925846863],"iteration":297,"passed_time":2.028033031,"remaining_time":4.777446939},
{"learn":[0.3922546005],"iteration":298,"passed_time":2.03608604,"remaining_time":4.773566267},
{"learn":[0.3919261551],"iteration":299,"passed_time":2.04031102,"remaining_time":4.760725712},
{"learn":[0.3915911102],"iteration":300,"passed_time":2.044036526,"remaining_time":4.746782498},
{"learn":[0.3913692474],"iteration":301,"passed_time":2.051751182,"remaining_time":4.742126904},
{"learn":[0.390977211],"iteration":302,"passed_time":2.05571838,"remaining_time":4.72883073},
{"learn":[0.3906950378],"iteration":303,"passed_time":2.059426268,"remaining_time":4.715002246},
{"learn":[0.3902910614],"iteration":304,"passed_time":2.067241515,"remaining_time":4.710599517},
{"learn":[0.3899391174],"iteration":305,"passed_time":2.070980447,"remaining_time":4.69692951},
{"learn":[0.3895878601],"iteration":306,"passed_time":2.074794835,"remaining_time":4.683494529},
{"learn":[0.3889812469],"iteration":307,"passed_time":2.080949843,"remaining_time":4.675380816},
{"learn":[0.388643074],"iteration":308,"passed_time":2.085785863,"remaining_time":4.664330199},
{"learn":[0.3882594299],"iteration":309,"passed_time":2.091587034,"remaining_time":4.655467914},
{"learn":[0.3879311371],"iteration":310,"passed_time":2.099522627,"remaining_time":4.651353987},
{"learn":[0.3877335358],"iteration":311,"passed_time":2.103735063,"remaining_time":4.639005523},
{"learn":[0.3873588562],"iteration":312,"passed_time":2.107334821,"remaining_time":4.625364289},
{"learn":[0.3870358276],"iteration":313,"passed_time":2.115524372,"remaining_time":4.621814392},
{"learn":[0.3866959381],"iteration":314,"passed_time":2.120123444,"remaining_time":4.610427172},
{"learn":[0.386411705],"iteration":315,"passed_time":2.124743338,"remaining_time":4.599127984},
{"learn":[0.386078186],"iteration":316,"passed_time":2.133035932,"remaining_time":4.595784042},
{"learn":[0.3855461884],"iteration":317,"passed_time":2.136590753,"remaining_time":4.582248093},
{"learn":[0.3852220917],"iteration":318,"passed_time":2.140321737,"remaining_time":4.569150793},
{"learn":[0.3848892212],"iteration":319,"passed_time":2.148191803,"remaining_time":4.564907582},
{"learn":[0.3846455765],"iteration":320,"passed_time":2.152046334,"remaining_time":4.552147852},
{"learn":[0.3842671967],"iteration":321,"passed_time":2.156507543,"remaining_time":4.540720851},
{"learn":[0.3839632034],"iteration":322,"passed_time":2.167820396,"remaining_time":4.543697858},
{"learn":[0.3834259796],"iteration":323,"passed_time":2.172089555,"remaining_time":4.531890553},
{"learn":[0.3833002472],"iteration":324,"passed_time":2.180116937,"remaining_time":4.527935178},
{"learn":[0.3830335617],"iteration":325,"passed_time":2.184812443,"remaining_time":4.517066217},
{"learn":[0.3827693939],"iteration":326,"passed_time":2.189061666,"remaining_time":4.505316517},
{"learn":[0.3823522949],"iteration":327,"passed_time":2.196571268,"remaining_time":4.500292354},
{"learn":[0.3820573044],"iteration":328,"passed_time":2.200499751,"remaining_time":4.487949341},
{"learn":[0.3816798401],"iteration":329,"passed_time":2.204163028,"remaining_time":4.475118875},
{"learn":[0.381469574],"iteration":330,"passed_time":2.212624039,"remaining_time":4.472040732},
{"learn":[0.3811225891],"iteration":331,"passed_time":2.216206675,"remaining_time":4.459114636},
{"learn":[0.3807967758],"iteration":332,"passed_time":2.220178236,"remaining_time":4.447023675},
{"learn":[0.3804940033],"iteration":333,"passed_time":2.227892224,"remaining_time":4.442443777},
{"learn":[0.3801686096],"iteration":334,"passed_time":2.231720836,"remaining_time":4.430132405},
{"learn":[0.3799773407],"iteration":335,"passed_time":2.235560968,"remaining_time":4.417894294},
{"learn":[0.3796243286],"iteration":336,"passed_time":2.241598689,"remaining_time":4.410029469},
{"learn":[0.3791815186],"iteration":337,"passed_time":2.245790863,"remaining_time":4.398560802},
{"learn":[0.3788895798],"iteration":338,"passed_time":2.249566258,"remaining_time":4.386322408},
{"learn":[0.3784259033],"iteration":339,"passed_time":2.253654929,"remaining_time":4.374741922},
{"learn":[0.3780527115],"iteration":340,"passed_time":2.261179571,"remaining_time":4.369845564},
{"learn":[0.3776556778],"iteration":341,"passed_time":2.264847642,"remaining_time":4.357513885},
{"learn":[0.3773783875],"iteration":342,"passed_time":2.268547542,"remaining_time":4.345293688},
{"learn":[0.3771422577],"iteration":343,"passed_time":2.276297458,"remaining_time":4.340846315},
{"learn":[0.376907959],"iteration":344,"passed_time":2.279945947,"remaining_time":4.32859303},
{"learn":[0.3765201569],"iteration":345,"passed_time":2.283762973,"remaining_time":4.316708048},
{"learn":[0.3762814331],"iteration":346,"passed_time":2.291631584,"remaining_time":4.312494018},
{"learn":[0.3760123444],"iteration":347,"passed_time":2.296336251,"remaining_time":4.302331136},
{"learn":[0.3757540131],"iteration":348,"passed_time":2.30130725,"remaining_time":4.292696332},
{"learn":[0.3754929733],"iteration":349,"passed_time":2.30873079,"remaining_time":4.287642896},
{"learn":[0.375278511],"iteration":350,"passed_time":2.312371167,"remaining_time":4.275580875},
{"learn":[0.374962616],"iteration":351,"passed_time":2.31595875,"remaining_time":4.263469518},
{"learn":[0.3747090149],"iteration":352,"passed_time":2.323162472,"remaining_time":4.258034333},
{"learn":[0.3743921661],"iteration":353,"passed_time":2.326900245,"remaining_time":4.246264289},
{"learn":[0.3741907501],"iteration":354,"passed_time":2.330504961,"remaining_time":4.234297746},
{"learn":[0.3737662506],"iteration":355,"passed_time":2.335914233,"remaining_time":4.225642601},
{"learn":[0.3734911346],"iteration":356,"passed_time":2.342514576,"remaining_time":4.219150904},
{"learn":[0.3732007599],"iteration":357,"passed_time":2.3461806,"remaining_time":4.207396494},
{"learn":[0.3729653549],"iteration":358,"passed_time":2.351233621,"remaining_time":4.198163651},
{"learn":[0.3727790451],"iteration":359,"passed_time":2.355789444,"remaining_time":4.188070124},
{"learn":[0.372579155],"iteration":360,"passed_time":2.359463255,"remaining_time":4.176446039},
{"learn":[0.3722839355],"iteration":361,"passed_time":2.363056839,"remaining_time":4.164724483},
{"learn":[0.3722708511],"iteration":362,"passed_time":2.365240449,"remaining_time":4.150573461},
{"learn":[0.3721618652],"iteration":363,"passed_time":2.370112694,"remaining_time":4.141185917},
{"learn":[0.3719201279],"iteration":364,"passed_time":2.375571866,"remaining_time":4.132844204},
{"learn":[0.371689949],"iteration":365,"passed_time":2.385789267,"remaining_time":4.132760642},
{"learn":[0.3712368011],"iteration":366,"passed_time":2.392921055,"remaining_time":4.127299803},
{"learn":[0.3710313416],"iteration":367,"passed_time":2.403849684,"remaining_time":4.128350544},
{"learn":[0.3706565094],"iteration":368,"passed_time":2.410409579,"remaining_time":4.121865702},
{"learn":[0.3704872894],"iteration":369,"passed_time":2.416671062,"remaining_time":4.11487235},
{"learn":[0.3700812149],"iteration":370,"passed_time":2.421207539,"remaining_time":4.104958334},
{"learn":[0.3698779678],"iteration":371,"passed_time":2.42754911,"remaining_time":4.098120541},
{"learn":[0.3694269562],"iteration":372,"passed_time":2.437283267,"remaining_time":4.096988227},
{"learn":[0.3691957092],"iteration":373,"passed_time":2.444925415,"remaining_time":4.092308316},
{"learn":[0.3688741302],"iteration":374,"passed_time":2.459872053,"remaining_time":4.099786755},
{"learn":[0.3685600281],"iteration":375,"passed_time":2.469671477,"remaining_time":4.098603728},
{"learn":[0.3682157135],"iteration":376,"passed_time":2.47648109,"remaining_time":4.092434268},
{"learn":[0.3679154205],"iteration":377,"passed_time":2.484433908,"remaining_time":4.088142568},
{"learn":[0.3676133728],"iteration":378,"passed_time":2.490062516,"remaining_time":4.080023278},
{"learn":[0.3672667694],"iteration":379,"passed_time":2.497706247,"remaining_time":4.07520493},
{"learn":[0.3671526718],"iteration":380,"passed_time":2.501565903,"remaining_time":4.064223868},
{"learn":[0.3669435883],"iteration":381,"passed_time":2.506366305,"remaining_time":4.054802033},
{"learn":[0.3665876007],"iteration":382,"passed_time":2.513053641,"remaining_time":4.048444117},
{"learn":[0.3663931656],"iteration":383,"passed_time":2.517368288,"remaining_time":4.038278295},
{"learn":[0.3661524582],"iteration":384,"passed_time":2.521820027,"remaining_time":4.028361861},
{"learn":[0.3657728958],"iteration":385,"passed_time":2.526095625,"remaining_time":4.018193559},
{"learn":[0.365404892],"iteration":386,"passed_time":2.532530206,"remaining_time":4.011475494},
{"learn":[0.3650994873],"iteration":387,"passed_time":2.537002833,"remaining_time":4.001664262},
{"learn":[0.3647833633],"iteration":388,"passed_time":2.542100686,"remaining_time":3.992862518},
{"learn":[0.3643869019],"iteration":389,"passed_time":2.550951917,"remaining_time":3.989950434},
{"learn":[0.3640850067],"iteration":390,"passed_time":2.556288904,"remaining_time":3.98153438},
{"learn":[0.3636894989],"iteration":391,"passed_time":2.563139493,"remaining_time":3.975481663},
{"learn":[0.3634848022],"iteration":392,"passed_time":2.568238091,"remaining_time":3.966718883},
{"learn":[0.3632360077],"iteration":393,"passed_time":2.575065329,"remaining_time":3.960633476},
{"learn":[0.3629981613],"iteration":394,"passed_time":2.580587686,"remaining_time":3.952545696},
{"learn":[0.3626937103],"iteration":395,"passed_time":2.587851403,"remaining_time":3.947126888},
{"learn":[0.3621846771],"iteration":396,"passed_time":2.600357847,"remaining_time":3.949661918},
{"learn":[0.3618687439],"iteration":397,"passed_time":2.610755214,"remaining_time":3.948931254},
{"learn":[0.3615171051],"iteration":398,"passed_time":2.617972591,"remaining_time":3.943362223},
{"learn":[0.3613219833],"iteration":399,"passed_time":2.627293948,"remaining_time":3.940940923},
{"learn":[0.3610647583],"iteration":400,"passed_time":2.632651042,"remaining_time":3.932563527},
{"learn":[0.3608608246],"iteration":401,"passed_time":2.63974026,"remaining_time":3.9267778},
{"learn":[0.3605570984],"iteration":402,"passed_time":2.646596461,"remaining_time":3.920640415},
{"learn":[0.360225563],"iteration":403,"passed_time":2.657615365,"remaining_time":3.920640489},
{"learn":[0.3600304413],"iteration":404,"passed_time":2.66726703,"remaining_time":3.918577489},
{"learn":[0.3597893524],"iteration":405,"passed_time":2.678995804,"remaining_time":3.919516028},
{"learn":[0.3594527054],"iteration":406,"passed_time":2.692470951,"remaining_time":3.922936791},
{"learn":[0.3592749786],"iteration":407,"passed_time":2.699551245,"remaining_time":3.916995925},
{"learn":[0.3589710999],"iteration":408,"passed_time":2.705937829,"remaining_time":3.910047083},
{"learn":[0.3586542511],"iteration":409,"passed_time":2.711028639,"remaining_time":3.901236333},
{"learn":[0.3584699631],"iteration":410,"passed_time":2.717895969,"remaining_time":3.8949896},
{"learn":[0.3581532288],"iteration":411,"passed_time":2.724111527,"remaining_time":3.887809655},
{"learn":[0.3579029083],"iteration":412,"passed_time":2.728721599,"remaining_time":3.878352491},
{"learn":[0.3576491928],"iteration":413,"passed_time":2.732983182,"remaining_time":3.868425471},
{"learn":[0.3573273468],"iteration":414,"passed_time":2.739015364,"remaining_time":3.861021658},
{"learn":[0.3571086121],"iteration":415,"passed_time":2.743261818,"remaining_time":3.851117552},
{"learn":[0.356826973],"iteration":416,"passed_time":2.74808116,"remaining_time":3.842041526},
{"learn":[0.356583519],"iteration":417,"passed_time":2.754129413,"remaining_time":3.834696934},
{"learn":[0.3563423157],"iteration":418,"passed_time":2.758523624,"remaining_time":3.825064977},
{"learn":[0.3561372757],"iteration":419,"passed_time":2.762834888,"remaining_time":3.815343417},
{"learn":[0.3558634949],"iteration":420,"passed_time":2.767597236,"remaining_time":3.806267932},
{"learn":[0.3555419159],"iteration":421,"passed_time":2.772635149,"remaining_time":3.797590323},
{"learn":[0.3553527069],"iteration":422,"passed_time":2.777228231,"remaining_time":3.788323142},
{"learn":[0.3550827789],"iteration":423,"passed_time":2.782218462,"remaining_time":3.779617534},
{"learn":[0.3548559189],"iteration":424,"passed_time":2.787938772,"remaining_time":3.771917162},
{"learn":[0.3546447372],"iteration":425,"passed_time":2.794766156,"remaining_time":3.765717778},
{"learn":[0.3544681931],"iteration":426,"passed_time":2.801431723,"remaining_time":3.759298308},
{"learn":[0.3540786743],"iteration":427,"passed_time":2.805609035,"remaining_time":3.749552262},
{"learn":[0.3537947464],"iteration":428,"passed_time":2.809368924,"remaining_time":3.739276587},
{"learn":[0.3535238647],"iteration":429,"passed_time":2.812922242,"remaining_time":3.728757391},
{"learn":[0.3532907867],"iteration":430,"passed_time":2.818937859,"remaining_time":3.721521211},
{"learn":[0.3531904984],"iteration":431,"passed_time":2.823084663,"remaining_time":3.711833538},
{"learn":[0.352926712],"iteration":432,"passed_time":2.826710792,"remaining_time":3.701489651},
{"learn":[0.3527424622],"iteration":433,"passed_time":2.83131399,"remaining_time":3.692450965},
{"learn":[0.3524924469],"iteration":434,"passed_time":2.835095417,"remaining_time":3.682365312},
{"learn":[0.3521780014],"iteration":435,"passed_time":2.838874058,"remaining_time":3.672304974},
{"learn":[0.3519773865],"iteration":436,"passed_time":2.842411318,"remaining_time":3.661962407},
{"learn":[0.3518375778],"iteration":437,"passed_time":2.846517512,"remaining_time":3.652380918},
{"learn":[0.3515927887],"iteration":438,"passed_time":2.854084564,"remaining_time":3.647247017},
{"learn":[0.3513677216],"iteration":439,"passed_time":2.857886448,"remaining_time":3.637310025},
{"learn":[0.3512030029],"iteration":440,"passed_time":2.861980682,"remaining_time":3.627771432},
{"learn":[0.350942688],"iteration":441,"passed_time":2.866014559,"remaining_time":3.618181276},
{"learn":[0.3506721115],"iteration":442,"passed_time":2.869749751,"remaining_time":3.608240658},
{"learn":[0.3504125977],"iteration":443,"passed_time":2.873379349,"remaining_time":3.598195762},
{"learn":[0.3501663971],"iteration":444,"passed_time":2.878122556,"remaining_time":3.58956858},
{"learn":[0.349894104],"iteration":445,"passed_time":2.882164236,"remaining_time":3.580087414},
{"learn":[0.3496931458],"iteration":446,"passed_time":2.886056809,"remaining_time":3.570446119},
{"learn":[0.349445343],"iteration":447,"passed_time":2.889801767,"remaining_time":3.560648605},
{"learn":[0.349161911],"iteration":448,"passed_time":2.895420513,"remaining_time":3.553177511},
{"learn":[0.3488707352],"iteration":449,"passed_time":2.900046167,"remaining_time":3.544500871},
{"learn":[0.3485304642],"iteration":450,"passed_time":2.904568939,"remaining_time":3.535716957},
{"learn":[0.3482740021],"iteration":451,"passed_time":2.910029565,"remaining_time":3.528088941},
{"learn":[0.3480516815],"iteration":452,"passed_time":2.914523634,"remaining_time":3.519303373},
{"learn":[0.3477187347],"iteration":453,"passed_time":2.919451035,"remaining_time":3.511057853},
{"learn":[0.3476027679],"iteration":454,"passed_time":2.923142144,"remaining_time":3.501346084},
{"learn":[0.3472922516],"iteration":455,"passed_time":2.928653615,"remaining_time":3.493832382},
{"learn":[0.3469013596],"iteration":456,"passed_time":2.932538044,"remaining_time":3.484394218},
{"learn":[0.3465573883],"iteration":457,"passed_time":2.936241356,"remaining_time":3.474765971},
{"learn":[0.3461663818],"iteration":458,"passed_time":2.939933006,"remaining_time":3.465149796},
{"learn":[0.3459075546],"iteration":459,"passed_time":2.945213819,"remaining_time":3.457424918},
{"learn":[0.3457651901],"iteration":460,"passed_time":2.949053962,"remaining_time":3.448026216},
{"learn":[0.3455756378],"iteration":461,"passed_time":2.952759594,"remaining_time":3.438494938},
{"learn":[0.345302124],"iteration":462,"passed_time":2.957719649,"remaining_time":3.43044374},
{"learn":[0.3451203918],"iteration":463,"passed_time":2.961852332,"remaining_time":3.421450107},
{"learn":[0.3448110962],"iteration":464,"passed_time":2.965777937,"remaining_time":3.412239132},
{"learn":[0.3444792938],"iteration":465,"passed_time":2.969540425,"remaining_time":3.40286392},
{"learn":[0.3442758942],"iteration":466,"passed_time":2.975215428,"remaining_time":3.395695552},
{"learn":[0.3438290787],"iteration":467,"passed_time":2.979116502,"remaining_time":3.386517049},
{"learn":[0.3435930634],"iteration":468,"passed_time":2.982935576,"remaining_time":3.377268211},
{"learn":[0.3433877563],"iteration":469,"passed_time":2.986658667,"remaining_time":3.367934242},
{"learn":[0.3430236816],"iteration":470,"passed_time":2.992460242,"remaining_time":3.360958531},
{"learn":[0.3427732086],"iteration":471,"passed_time":2.996444475,"remaining_time":3.351954836},
{"learn":[0.3425331497],"iteration":472,"passed_time":3.000194902,"remaining_time":3.342711867},
{"learn":[0.3422752762],"iteration":473,"passed_time":3.005467243,"remaining_time":3.335180949},
{"learn":[0.3420978546],"iteration":474,"passed_time":3.009434069,"remaining_time":3.326216602},
{"learn":[0.3417771912],"iteration":475,"passed_time":3.013067022,"remaining_time":3.316905714},
{"learn":[0.3416876221],"iteration":476,"passed_time":3.016808605,"remaining_time":3.307737736},
{"learn":[0.3415338898],"iteration":477,"passed_time":3.022602559,"remaining_time":3.300833756},
{"learn":[0.3413469315],"iteration":478,"passed_time":3.02748795,"remaining_time":3.292946184},
{"learn":[0.3411927032],"iteration":479,"passed_time":3.031209312,"remaining_time":3.283810088},
{"learn":[0.3410151672],"iteration":480,"passed_time":3.035048075,"remaining_time":3.274823183},
{"learn":[0.3407460785],"iteration":481,"passed_time":3.040552795,"remaining_time":3.267648024},
{"learn":[0.34045578],"iteration":482,"passed_time":3.045125625,"remaining_time":3.259482294},
{"learn":[0.3401631165],"iteration":483,"passed_time":3.050094257,"remaining_time":3.251753381},
{"learn":[0.3399072266],"iteration":484,"passed_time":3.056954333,"remaining_time":3.246044292},
{"learn":[0.3396005249],"iteration":485,"passed_time":3.060832961,"remaining_time":3.237177247},
{"learn":[0.3395013809],"iteration":486,"passed_time":3.064507265,"remaining_time":3.228115456},
{"learn":[0.3393063736],"iteration":487,"passed_time":3.070243142,"remaining_time":3.221238706},
{"learn":[0.3390705872],"iteration":488,"passed_time":3.07494834,"remaining_time":3.213289575},
{"learn":[0.3388891602],"iteration":489,"passed_time":3.079578626,"remaining_time":3.205275713},
{"learn":[0.3386709976],"iteration":490,"passed_time":3.084994977,"remaining_time":3.198090516},
{"learn":[0.33842453],"iteration":491,"passed_time":3.090004446,"remaining_time":3.190492395},
{"learn":[0.3380890656],"iteration":492,"passed_time":3.097283902,"remaining_time":3.185239226},
{"learn":[0.3379451752],"iteration":493,"passed_time":3.10557363,"remaining_time":3.181012666},
{"learn":[0.3377172852],"iteration":494,"passed_time":3.109946053,"remaining_time":3.172773246},
{"learn":[0.337541275],"iteration":495,"passed_time":3.114827159,"remaining_time":3.165066307},
{"learn":[0.3373295593],"iteration":496,"passed_time":3.12226522,"remaining_time":3.159958563},
{"learn":[0.3370999908],"iteration":497,"passed_time":3.126057912,"remaining_time":3.151166811},
{"learn":[0.336829834],"iteration":498,"passed_time":3.129905078,"remaining_time":3.142449788},
{"learn":[0.3366542816],"iteration":499,"passed_time":3.138997357,"remaining_time":3.138997357},
{"learn":[0.3364989853],"iteration":500,"passed_time":3.142656527,"remaining_time":3.130110992},
{"learn":[0.3362347794],"iteration":501,"passed_time":3.146463479,"remaining_time":3.121392057},
{"learn":[0.3360423279],"iteration":502,"passed_time":3.153599605,"remaining_time":3.115982115},
{"learn":[0.3358627319],"iteration":503,"passed_time":3.157887099,"remaining_time":3.107761907},
{"learn":[0.3355781555],"iteration":504,"passed_time":3.161634825,"remaining_time":3.099028194},
{"learn":[0.3352046967],"iteration":505,"passed_time":3.169395983,"remaining_time":3.094232442},
{"learn":[0.3349909973],"iteration":506,"passed_time":3.173125533,"remaining_time":3.08550471},
{"learn":[0.3346312332],"iteration":507,"passed_time":3.177108052,"remaining_time":3.077041657},
{"learn":[0.3344454956],"iteration":508,"passed_time":3.184288981,"remaining_time":3.071681512},
{"learn":[0.3341569519],"iteration":509,"passed_time":3.188165934,"remaining_time":3.063139819},
{"learn":[0.3338618469],"iteration":510,"passed_time":3.191752994,"remaining_time":3.054338971},
{"learn":[0.3337751007],"iteration":511,"passed_time":3.195291296,"remaining_time":3.045512016},
{"learn":[0.3335238647],"iteration":512,"passed_time":3.199855418,"remaining_time":3.03767951},
{"learn":[0.3333099365],"iteration":513,"passed_time":3.203541758,"remaining_time":3.029029755},
{"learn":[0.3330334473],"iteration":514,"passed_time":3.207038561,"remaining_time":3.020220781},
{"learn":[0.3328476715],"iteration":515,"passed_time":3.214001039,"remaining_time":3.014683145},
{"learn":[0.3325410461],"iteration":516,"passed_time":3.218442974,"remaining_time":3.006785215},
{"learn":[0.3323853302],"iteration":517,"passed_time":3.222151945,"remaining_time":2.998218605},
{"learn":[0.3320342255],"iteration":518,"passed_time":3.227876947,"remaining_time":2.991539136},
{"learn":[0.3318702698],"iteration":519,"passed_time":3.233300483,"remaining_time":2.984585061},
{"learn":[0.3317146683],"iteration":520,"passed_time":3.237202192,"remaining_time":2.976237716},
{"learn":[0.3315393066],"iteration":521,"passed_time":3.242215099,"remaining_time":2.968924937},
{"learn":[0.3313183975],"iteration":522,"passed_time":3.247208189,"remaining_time":2.96160288},
{"learn":[0.3310933304],"iteration":523,"passed_time":3.251812679,"remaining_time":2.953936708},
{"learn":[0.3309259033],"iteration":524,"passed_time":3.256339964,"remaining_time":2.946212349},
{"learn":[0.3307560349],"iteration":525,"passed_time":3.262854558,"remaining_time":2.94029099},
{"learn":[0.3305031967],"iteration":526,"passed_time":3.267206769,"remaining_time":2.932426569},
{"learn":[0.330135231],"iteration":527,"passed_time":3.271798181,"remaining_time":2.924789283},
{"learn":[0.3298274994],"iteration":528,"passed_time":3.277958459,"remaining_time":2.918560367},
{"learn":[0.3295684052],"iteration":529,"passed_time":3.281772655,"remaining_time":2.910251223},
{"learn":[0.3293937683],"iteration":530,"passed_time":3.285702703,"remaining_time":2.902061333},
{"learn":[0.3291896057],"iteration":531,"passed_time":3.292884416,"remaining_time":2.896747945},
{"learn":[0.3289892197],"iteration":532,"passed_time":3.296760902,"remaining_time":2.888531597},
{"learn":[0.3286513519],"iteration":533,"passed_time":3.300344387,"remaining_time":2.880075814},
{"learn":[0.3284567261],"iteration":534,"passed_time":3.307243549,"remaining_time":2.874520094},
{"learn":[0.3280827332],"iteration":535,"passed_time":3.311028069,"remaining_time":2.866263105},
{"learn":[0.32786026],"iteration":536,"passed_time":3.314821245,"remaining_time":2.858030236},
{"learn":[0.3277479935],"iteration":537,"passed_time":3.320537673,"remaining_time":2.851465437},
{"learn":[0.3275612259],"iteration":538,"passed_time":3.324651219,"remaining_time":2.843532861},
{"learn":[0.327361908],"iteration":539,"passed_time":3.32861814,"remaining_time":2.835489526},
{"learn":[0.3271997833],"iteration":540,"passed_time":3.332238938,"remaining_time":2.827167602},
{"learn":[0.326946106],"iteration":541,"passed_time":3.339060455,"remaining_time":2.821567691},
{"learn":[0.3268200302],"iteration":542,"passed_time":3.343006007,"remaining_time":2.813542809},
{"learn":[0.3264575195],"iteration":543,"passed_time":3.34879612,"remaining_time":2.807079101},
{"learn":[0.3263644409],"iteration":544,"passed_time":3.355588291,"remaining_time":2.801454445},
{"learn":[0.3261592102],"iteration":545,"passed_time":3.35956035,"remaining_time":2.793480584},
{"learn":[0.3259996796],"iteration":546,"passed_time":3.363277037,"remaining_time":2.785309868},
{"learn":[0.3254921722],"iteration":547,"passed_time":3.369336453,"remaining_time":2.779087731},
{"learn":[0.3253363419],"iteration":548,"passed_time":3.373305506,"remaining_time":2.771148968},
{"learn":[0.3251584625],"iteration":549,"passed_time":3.377083183,"remaining_time":2.763068059},
{"learn":[0.324994278],"iteration":550,"passed_time":3.381051173,"remaining_time":2.755157853},
{"learn":[0.3248710632],"iteration":551,"passed_time":3.387763268,"remaining_time":2.749489029},
{"learn":[0.3245890045],"iteration":552,"passed_time":3.391397733,"remaining_time":2.741328728},
{"learn":[0.3243471909],"iteration":553,"passed_time":3.395257349,"remaining_time":2.733366025},
{"learn":[0.3241233826],"iteration":554,"passed_time":3.401654161,"remaining_time":2.727452435},
{"learn":[0.3237549591],"iteration":555,"passed_time":3.40526772,"remaining_time":2.71931451},
{"learn":[0.3235764313],"iteration":556,"passed_time":3.409348498,"remaining_time":2.711564425},
{"learn":[0.3233175659],"iteration":557,"passed_time":3.414215332,"remaining_time":2.704450138},
{"learn":[0.3230760193],"iteration":558,"passed_time":3.420289374,"remaining_time":2.698296268},
{"learn":[0.3229804993],"iteration":559,"passed_time":3.424933816,"remaining_time":2.691019427},
{"learn":[0.3227911377],"iteration":560,"passed_time":3.435727925,"remaining_time":2.688564277},
{"learn":[0.3223993683],"iteration":561,"passed_time":3.442051294,"remaining_time":2.682595136},
{"learn":[0.3221683121],"iteration":562,"passed_time":3.448620324,"remaining_time":2.67681542},
{"learn":[0.3219459152],"iteration":563,"passed_time":3.454860886,"remaining_time":2.670778983},
{"learn":[0.3217462158],"iteration":564,"passed_time":3.458820959,"remaining_time":2.662986048},
{"learn":[0.321504097],"iteration":565,"passed_time":3.466663976,"remaining_time":2.658184038},
{"learn":[0.3212245178],"iteration":566,"passed_time":3.472100784,"remaining_time":2.651533756},
{"learn":[0.3210870743],"iteration":567,"passed_time":3.476801688,"remaining_time":2.644328044},
{"learn":[0.3208448029],"iteration":568,"passed_time":3.487889676,"remaining_time":2.641969157},
{"learn":[0.3206504059],"iteration":569,"passed_time":3.492659979,"remaining_time":2.634813668},
{"learn":[0.3203591919],"iteration":570,"passed_time":3.501094767,"remaining_time":2.630419711},
{"learn":[0.3202634811],"iteration":571,"passed_time":3.504712239,"remaining_time":2.62240706},
{"learn":[0.3200875854],"iteration":572,"passed_time":3.508555495,"remaining_time":2.614578004},
{"learn":[0.3197549629],"iteration":573,"passed_time":3.516715059,"remaining_time":2.609966228},
{"learn":[0.3195203018],"iteration":574,"passed_time":3.520372799,"remaining_time":2.602014677},
{"learn":[0.3193181038],"iteration":575,"passed_time":3.524133528,"remaining_time":2.594153847},
{"learn":[0.3191021347],"iteration":576,"passed_time":3.533593005,"remaining_time":2.590484993},
{"learn":[0.3188373756],"iteration":577,"passed_time":3.537240719,"remaining_time":2.582552913},
{"learn":[0.3186525154],"iteration":578,"passed_time":3.542433405,"remaining_time":2.575759004},
{"learn":[0.318456192],"iteration":579,"passed_time":3.54805831,"remaining_time":2.569283604},
{"learn":[0.3181190491],"iteration":580,"passed_time":3.55372735,"remaining_time":2.56284296},
{"learn":[0.3179348373],"iteration":581,"passed_time":3.560332419,"remaining_time":2.557077235},
{"learn":[0.317801609],"iteration":582,"passed_time":3.566620312,"remaining_time":2.551081767},
{"learn":[0.3176235962],"iteration":583,"passed_time":3.570786024,"remaining_time":2.543573606},
{"learn":[0.3173163033],"iteration":584,"passed_time":3.579156892,"remaining_time":2.539060017},
{"learn":[0.3170354843],"iteration":585,"passed_time":3.582924335,"remaining_time":2.531281015},
{"learn":[0.3168333435],"iteration":586,"passed_time":3.586574033,"remaining_time":2.523432837},
{"learn":[0.3167417717],"iteration":587,"passed_time":3.597083252,"remaining_time":2.520405272},
{"learn":[0.3164202309],"iteration":588,"passed_time":3.601417912,"remaining_time":2.513043739},
{"learn":[0.3161467552],"iteration":589,"passed_time":3.609713596,"remaining_time":2.508445042},
{"learn":[0.3159289169],"iteration":590,"passed_time":3.614095991,"remaining_time":2.501125652},
{"learn":[0.3156139374],"iteration":591,"passed_time":3.618566594,"remaining_time":2.493876977},
{"learn":[0.3155412674],"iteration":592,"passed_time":3.625380297,"remaining_time":2.488245836},
{"learn":[0.3152375031],"iteration":593,"passed_time":3.629914043,"remaining_time":2.48105236},
{"learn":[0.3150119781],"iteration":594,"passed_time":3.634605084,"remaining_time":2.473974889},
{"learn":[0.3148833847],"iteration":595,"passed_time":3.641971437,"remaining_time":2.468718894},
{"learn":[0.3145746613],"iteration":596,"passed_time":3.646970256,"remaining_time":2.461857643},
{"learn":[0.3142639542],"iteration":597,"passed_time":3.654415225,"remaining_time":2.456647024},
{"learn":[0.3140426445],"iteration":598,"passed_time":3.665161267,"remaining_time":2.453638845},
{"learn":[0.3136526489],"iteration":599,"passed_time":3.674948915,"remaining_time":2.449965943},
{"learn":[0.313464489],"iteration":600,"passed_time":3.679668097,"remaining_time":2.442907772},
{"learn":[0.3130922318],"iteration":601,"passed_time":3.687193729,"remaining_time":2.437712797},
{"learn":[0.3128972816],"iteration":602,"passed_time":3.693123672,"remaining_time":2.431459532},
{"learn":[0.3127074623],"iteration":603,"passed_time":3.697580436,"remaining_time":2.424241478},
{"learn":[0.3125550842],"iteration":604,"passed_time":3.706297847,"remaining_time":2.419814297},
{"learn":[0.3123369789],"iteration":605,"passed_time":3.719490844,"remaining_time":2.418282826},
{"learn":[0.3121248055],"iteration":606,"passed_time":3.728263073,"remaining_time":2.413850721},
{"learn":[0.3118213272],"iteration":607,"passed_time":3.743534986,"remaining_time":2.413594925},
{"learn":[0.3115926743],"iteration":608,"passed_time":3.748719783,"remaining_time":2.406813522},
{"learn":[0.3114749718],"iteration":609,"passed_time":3.759942081,"remaining_time":2.403897396},
{"learn":[0.3112695313],"iteration":610,"passed_time":3.768442612,"remaining_time":2.399221237},
{"learn":[0.3110703659],"iteration":611,"passed_time":3.773094896,"remaining_time":2.392092843},
{"learn":[0.3109647369],"iteration":612,"passed_time":3.781925971,"remaining_time":2.387610687},
{"learn":[0.3108355522],"iteration":613,"passed_time":3.786392767,"remaining_time":2.380370697},
{"learn":[0.3106159592],"iteration":614,"passed_time":3.790774511,"remaining_time":2.373086482},
{"learn":[0.3103837776],"iteration":615,"passed_time":3.806402326,"remaining_time":2.372822229},
{"learn":[0.3100948334],"iteration":616,"passed_time":3.820843776,"remaining_time":2.371771745},
{"learn":[0.3095957184],"iteration":617,"passed_time":3.828858636,"remaining_time":2.3667055},
{"learn":[0.3094244766],"iteration":618,"passed_time":3.835875546,"remaining_time":2.361015481},
{"learn":[0.3093004227],"iteration":619,"passed_time":3.845822087,"remaining_time":2.357116763},
{"learn":[0.3090413284],"iteration":620,"passed_time":3.853485962,"remaining_time":2.351805442},
{"learn":[0.3089145088],"iteration":621,"passed_time":3.866821785,"remaining_time":2.349933497},
{"learn":[0.3087763214],"iteration":622,"passed_time":3.87146355,"remaining_time":2.342763657},
{"learn":[0.308609848],"iteration":623,"passed_time":3.88238601,"remaining_time":2.339386442},
{"learn":[0.3082510185],"iteration":624,"passed_time":3.887840266,"remaining_time":2.33270416},
{"learn":[0.308060379],"iteration":625,"passed_time":3.897561671,"remaining_time":2.328575183},
{"learn":[0.3077663994],"iteration":626,"passed_time":3.902438856,"remaining_time":2.32154656},
{"learn":[0.3075415993],"iteration":627,"passed_time":3.918614308,"remaining_time":2.321217393},
{"learn":[0.3073562431],"iteration":628,"passed_time":3.930274847,"remaining_time":2.31817483},
{"learn":[0.307179184],"iteration":629,"passed_time":3.934761571,"remaining_time":2.310891716},
{"learn":[0.3069557571],"iteration":630,"passed_time":3.945448891,"remaining_time":2.307243488},
{"learn":[0.3067157173],"iteration":631,"passed_time":3.950556018,"remaining_time":2.300323757},
{"learn":[0.3065205193],"iteration":632,"passed_time":3.964451492,"remaining_time":2.298505051},
{"learn":[0.3063524818],"iteration":633,"passed_time":3.977873686,"remaining_time":2.29637503},
{"learn":[0.3061942482],"iteration":634,"passed_time":3.982694392,"remaining_time":2.289265281},
{"learn":[0.3060321426],"iteration":635,"passed_time":3.987154042,"remaining_time":2.281956087},
{"learn":[0.305826683],"iteration":636,"passed_time":3.995323647,"remaining_time":2.276769991},
{"learn":[0.3055662537],"iteration":637,"passed_time":3.998951562,"remaining_time":2.268997595},
{"learn":[0.3053410149],"iteration":638,"passed_time":4.002682304,"remaining_time":2.261296263},
{"learn":[0.3051167488],"iteration":639,"passed_time":4.018325466,"remaining_time":2.260308075},
{"learn":[0.3049098396],"iteration":640,"passed_time":4.027091628,"remaining_time":2.255422612},
{"learn":[0.3047551155],"iteration":641,"passed_time":4.031933688,"remaining_time":2.248336854},
{"learn":[0.3044951248],"iteration":642,"passed_time":4.038992871,"remaining_time":2.242489043},
{"learn":[0.3043637276],"iteration":643,"passed_time":4.043803049,"remaining_time":2.235394232},
{"learn":[0.3041725159],"iteration":644,"passed_time":4.048573733,"remaining_time":2.228284768},
{"learn":[0.3040360451],"iteration":645,"passed_time":4.057323924,"remaining_time":2.223363265},
{"learn":[0.3038839149],"iteration":646,"passed_time":4.0614025,"remaining_time":2.215881117},
{"learn":[0.3036834335],"iteration":647,"passed_time":4.065835415,"remaining_time":2.208601954},
{"learn":[0.3033913422],"iteration":648,"passed_time":4.073146954,"remaining_time":2.202888414},
{"learn":[0.3032493591],"iteration":649,"passed_time":4.077028646,"remaining_time":2.195323117},
{"learn":[0.303075943],"iteration":650,"passed_time":4.081255537,"remaining_time":2.187954197},
{"learn":[0.3028448105],"iteration":651,"passed_time":4.088459251,"remaining_time":2.182183772},
{"learn":[0.3026800156],"iteration":652,"passed_time":4.092974197,"remaining_time":2.174980163},
{"learn":[0.3024462509],"iteration":653,"passed_time":4.09729395,"remaining_time":2.167681509},
{"learn":[0.302324295],"iteration":654,"passed_time":4.105450448,"remaining_time":2.162412831},
{"learn":[0.302125721],"iteration":655,"passed_time":4.1103711,"remaining_time":2.155438504},
{"learn":[0.3018585968],"iteration":656,"passed_time":4.11464477,"remaining_time":2.148132657},
{"learn":[0.3016749954],"iteration":657,"passed_time":4.121809238,"remaining_time":2.14233854},
{"learn":[0.3014553833],"iteration":658,"passed_time":4.126059964,"remaining_time":2.135032546},
{"learn":[0.3012779617],"iteration":659,"passed_time":4.130402811,"remaining_time":2.127783266},
{"learn":[0.3010948563],"iteration":660,"passed_time":4.139246723,"remaining_time":2.122851194},
{"learn":[0.3009047318],"iteration":661,"passed_time":4.143619589,"remaining_time":2.115624503},
{"learn":[0.300730114],"iteration":662,"passed_time":4.149116674,"remaining_time":2.108977857},
{"learn":[0.3004180145],"iteration":663,"passed_time":4.154632318,"remaining_time":2.102344065},
{"learn":[0.3000567627],"iteration":664,"passed_time":4.159756396,"remaining_time":2.09551638},
{"learn":[0.2998077393],"iteration":665,"passed_time":4.166533911,"remaining_time":2.089523012},
{"learn":[0.2996093941],"iteration":666,"passed_time":4.173377801,"remaining_time":2.083560431},
{"learn":[0.2994458008],"iteration":667,"passed_time":4.181677092,"remaining_time":2.078318555},
{"learn":[0.2993201828],"iteration":668,"passed_time":4.186091169,"remaining_time":2.071145257},
{"learn":[0.2991432571],"iteration":669,"passed_time":4.190310978,"remaining_time":2.063884512},
{"learn":[0.2989477539],"iteration":670,"passed_time":4.203368972,"remaining_time":2.060966307},
{"learn":[0.2986499405],"iteration":671,"passed_time":4.209834512,"remaining_time":2.054800178},
{"learn":[0.2983485031],"iteration":672,"passed_time":4.218849285,"remaining_time":2.049871792},
{"learn":[0.2980553436],"iteration":673,"passed_time":4.223796562,"remaining_time":2.042963916},
{"learn":[0.2977612495],"iteration":674,"passed_time":4.230942916,"remaining_time":2.037120663},
{"learn":[0.2975422668],"iteration":675,"passed_time":4.236758985,"remaining_time":2.030635963},
{"learn":[0.2973316002],"iteration":676,"passed_time":4.24147015,"remaining_time":2.023626083},
{"learn":[0.2972436333],"iteration":677,"passed_time":4.251078992,"remaining_time":2.01894902},
{"learn":[0.2970335388],"iteration":678,"passed_time":4.256547085,"remaining_time":2.012299874},
{"learn":[0.296750145],"iteration":679,"passed_time":4.267951362,"remaining_time":2.0084477},
{"learn":[0.2965825844],"iteration":680,"passed_time":4.272305462,"remaining_time":2.00127084},
{"learn":[0.2964500999],"iteration":681,"passed_time":4.279412194,"remaining_time":1.995385745},
{"learn":[0.2962942123],"iteration":682,"passed_time":4.284071147,"remaining_time":1.988360986},
{"learn":[0.2960596466],"iteration":683,"passed_time":4.289052349,"remaining_time":1.981492021},
{"learn":[0.2958725357],"iteration":684,"passed_time":4.295836918,"remaining_time":1.975457853},
{"learn":[0.2956269073],"iteration":685,"passed_time":4.301335614,"remaining_time":1.968832919},
{"learn":[0.2954108429],"iteration":686,"passed_time":4.316159303,"remaining_time":1.96645977},
{"learn":[0.2952406311],"iteration":687,"passed_time":4.323717338,"remaining_time":1.960755537},
{"learn":[0.2950907516],"iteration":688,"passed_time":4.332222147,"remaining_time":1.955473277},
{"learn":[0.2948933792],"iteration":689,"passed_time":4.336875276,"remaining_time":1.948451211},
{"learn":[0.2946626854],"iteration":690,"passed_time":4.344574977,"remaining_time":1.942798362},
{"learn":[0.2944091988],"iteration":691,"passed_time":4.349884459,"remaining_time":1.936075742},
{"learn":[0.294224205],"iteration":692,"passed_time":4.367513713,"remaining_time":1.934814877},
{"learn":[0.2941188622],"iteration":693,"passed_time":4.383281044,"remaining_time":1.932685878},
{"learn":[0.2939092636],"iteration":694,"passed_time":4.387983752,"remaining_time":1.925661934},
{"learn":[0.293789711],"iteration":695,"passed_time":4.399089656,"remaining_time":1.921441459},
{"learn":[0.2935868454],"iteration":696,"passed_time":4.403176912,"remaining_time":1.914150078},
{"learn":[0.2933038139],"iteration":697,"passed_time":4.409289897,"remaining_time":1.907744339},
{"learn":[0.2930326653],"iteration":698,"passed_time":4.4153262,"remaining_time":1.901306418},
{"learn":[0.2927225113],"iteration":699,"passed_time":4.419595257,"remaining_time":1.894112253},
{"learn":[0.2925026321],"iteration":700,"passed_time":4.428474872,"remaining_time":1.888892991},
{"learn":[0.2923566818],"iteration":701,"passed_time":4.432067125,"remaining_time":1.881418808},
{"learn":[0.2922460175],"iteration":702,"passed_time":4.435661769,"remaining_time":1.873956679},
{"learn":[0.2920737839],"iteration":703,"passed_time":4.444084468,"remaining_time":1.868535515},
{"learn":[0.2919061279],"iteration":704,"passed_time":4.447832935,"remaining_time":1.861149952},
{"learn":[0.2916401482],"iteration":705,"passed_time":4.451442722,"remaining_time":1.853716941},
{"learn":[0.2913920975],"iteration":706,"passed_time":4.459578692,"remaining_time":1.848170519},
{"learn":[0.2913200378],"iteration":707,"passed_time":4.463653855,"remaining_time":1.840941985},
{"learn":[0.2911029625],"iteration":708,"passed_time":4.467805727,"remaining_time":1.833753832},
{"learn":[0.2909036255],"iteration":709,"passed_time":4.475481211,"remaining_time":1.828013452},
{"learn":[0.2907051849],"iteration":710,"passed_time":4.480156961,"remaining_time":1.821048329},
{"learn":[0.2904848671],"iteration":711,"passed_time":4.48481515,"remaining_time":1.814082533},
{"learn":[0.2902893066],"iteration":712,"passed_time":4.495051414,"remaining_time":1.809368522},
{"learn":[0.2899821472],"iteration":713,"passed_time":4.499184715,"remaining_time":1.802194438},
{"learn":[0.2896983337],"iteration":714,"passed_time":4.509822247,"remaining_time":1.797621455},
{"learn":[0.2895068932],"iteration":715,"passed_time":4.514621938,"remaining_time":1.790715964},
{"learn":[0.2892589569],"iteration":716,"passed_time":4.519231011,"remaining_time":1.78374111},
{"learn":[0.2891651154],"iteration":717,"passed_time":4.525665284,"remaining_time":1.777489708},
{"learn":[0.2889487839],"iteration":718,"passed_time":4.530106319,"remaining_time":1.770458798},
{"learn":[0.2886666489],"iteration":719,"passed_time":4.536736036,"remaining_time":1.764286236},
{"learn":[0.2884436607],"iteration":720,"passed_time":4.542111662,"remaining_time":1.75762712},
{"learn":[0.2882546997],"iteration":721,"passed_time":4.545812275,"remaining_time":1.75032661},
{"learn":[0.2880981827],"iteration":722,"passed_time":4.549979322,"remaining_time":1.743214761},
{"learn":[0.2879443932],"iteration":723,"passed_time":4.556580577,"remaining_time":1.737039005},
{"learn":[0.287793293],"iteration":724,"passed_time":4.560671549,"remaining_time":1.729909898},
{"learn":[0.2876553726],"iteration":725,"passed_time":4.564606756,"remaining_time":1.722730373},
{"learn":[0.2875421524],"iteration":726,"passed_time":4.573218068,"remaining_time":1.717315725},
{"learn":[0.2872020721],"iteration":727,"passed_time":4.576893602,"remaining_time":1.710048159},
{"learn":[0.2869012451],"iteration":728,"passed_time":4.580871226,"remaining_time":1.702902746},
{"learn":[0.2866601563],"iteration":729,"passed_time":4.588472215,"remaining_time":1.697106162},
{"learn":[0.2864993668],"iteration":730,"passed_time":4.5933072,"remaining_time":1.690286781},
{"learn":[0.286325779],"iteration":731,"passed_time":4.597243022,"remaining_time":1.68314362},
{"learn":[0.2861981773],"iteration":732,"passed_time":4.603013453,"remaining_time":1.676677479},
{"learn":[0.2859685707],"iteration":733,"passed_time":4.606790308,"remaining_time":1.669490766},
{"learn":[0.2857587814],"iteration":734,"passed_time":4.615684486,"remaining_time":1.664158352},
{"learn":[0.2856056976],"iteration":735,"passed_time":4.620009876,"remaining_time":1.657177456},
{"learn":[0.2853946304],"iteration":736,"passed_time":4.623763335,"remaining_time":1.64999967},
{"learn":[0.2852405167],"iteration":737,"passed_time":4.628029021,"remaining_time":1.643013013},
{"learn":[0.2850842667],"iteration":738,"passed_time":4.636627621,"remaining_time":1.637564018},
{"learn":[0.284912529],"iteration":739,"passed_time":4.640416931,"remaining_time":1.630416759},
{"learn":[0.2847473145],"iteration":740,"passed_time":4.647213743,"remaining_time":1.62432977},
{"learn":[0.2845782471],"iteration":741,"passed_time":4.652143869,"remaining_time":1.617591804},
{"learn":[0.2843898392],"iteration":742,"passed_time":4.656802626,"remaining_time":1.610764838},
{"learn":[0.2842607307],"iteration":743,"passed_time":4.665804501,"remaining_time":1.605438108},
{"learn":[0.2841406631],"iteration":744,"passed_time":4.669703242,"remaining_time":1.598354801},
{"learn":[0.2839204597],"iteration":745,"passed_time":4.67331861,"remaining_time":1.591183548},
{"learn":[0.2836450768],"iteration":746,"passed_time":4.681553321,"remaining_time":1.585586332},
{"learn":[0.2834025955],"iteration":747,"passed_time":4.685160962,"remaining_time":1.578423212},
{"learn":[0.2831361771],"iteration":748,"passed_time":4.689342141,"remaining_time":1.571461786},
{"learn":[0.2830142212],"iteration":749,"passed_time":4.697019609,"remaining_time":1.565673203},
{"learn":[0.2826562119],"iteration":750,"passed_time":4.70214189,"remaining_time":1.559032398},
{"learn":[0.2825281143],"iteration":751,"passed_time":4.705808185,"remaining_time":1.551915465},
{"learn":[0.2823542404],"iteration":752,"passed_time":4.712832006,"remaining_time":1.545909038},
{"learn":[0.2822692108],"iteration":753,"passed_time":4.716771618,"remaining_time":1.538893658},
{"learn":[0.2820298767],"iteration":754,"passed_time":4.720290588,"remaining_time":1.531749926},
{"learn":[0.2818774033],"iteration":755,"passed_time":4.726023881,"remaining_time":1.525330459},
{"learn":[0.281734848],"iteration":756,"passed_time":4.731328243,"remaining_time":1.518775116},
{"learn":[0.2815266609],"iteration":757,"passed_time":4.735063138,"remaining_time":1.511722005},
{"learn":[0.2814240265],"iteration":758,"passed_time":4.739072298,"remaining_time":1.504764722},
{"learn":[0.2811808968],"iteration":759,"passed_time":4.745901382,"remaining_time":1.4987057},
{"learn":[0.2808656883],"iteration":760,"passed_time":4.749529562,"remaining_time":1.491639376},
{"learn":[0.280611496],"iteration":761,"passed_time":4.753672152,"remaining_time":1.484742746},
{"learn":[0.2804436874],"iteration":762,"passed_time":4.761759064,"remaining_time":1.479078503},
{"learn":[0.2802771187],"iteration":763,"passed_time":4.765555621,"remaining_time":1.472082626},
{"learn":[0.2799722481],"iteration":764,"passed_time":4.769389442,"remaining_time":1.465106561},
{"learn":[0.279742527],"iteration":765,"passed_time":4.778022417,"remaining_time":1.459604759},
{"learn":[0.2794842148],"iteration":766,"passed_time":4.781752459,"remaining_time":1.452605375},
{"learn":[0.2792177582],"iteration":767,"passed_time":4.785528123,"remaining_time":1.445628287},
{"learn":[0.279038372],"iteration":768,"passed_time":4.792797832,"remaining_time":1.439709102},
{"learn":[0.2789664459],"iteration":769,"passed_time":4.797610858,"remaining_time":1.433052594},
{"learn":[0.2788148308],"iteration":770,"passed_time":4.803037735,"remaining_time":1.426583192},
{"learn":[0.2782385635],"iteration":771,"passed_time":4.811047778,"remaining_time":1.420879395},
{"learn":[0.277870903],"iteration":772,"passed_time":4.815303969,"remaining_time":1.414067272},
{"learn":[0.2776301193],"iteration":773,"passed_time":4.822327683,"remaining_time":1.40806984},
{"learn":[0.2773488235],"iteration":774,"passed_time":4.827877805,"remaining_time":1.401641943},
{"learn":[0.2772163773],"iteration":775,"passed_time":4.831941033,"remaining_time":1.394787102},
{"learn":[0.2770388794],"iteration":776,"passed_time":4.837842678,"remaining_time":1.388467075},
{"learn":[0.2768883514],"iteration":777,"passed_time":4.842570229,"remaining_time":1.381813099},
{"learn":[0.2766443825],"iteration":778,"passed_time":4.846319269,"remaining_time":1.374886468},
{"learn":[0.276560936],"iteration":779,"passed_time":4.850375723,"remaining_time":1.368054691},
{"learn":[0.2764017868],"iteration":780,"passed_time":4.85731867,"remaining_time":1.362039422},
{"learn":[0.2759999657],"iteration":781,"passed_time":4.863251241,"remaining_time":1.355740116},
{"learn":[0.2757842636],"iteration":782,"passed_time":4.867044241,"remaining_time":1.348848787},
{"learn":[0.2755502129],"iteration":783,"passed_time":4.873796076,"remaining_time":1.342780552},
{"learn":[0.2753855515],"iteration":784,"passed_time":4.877813953,"remaining_time":1.335961783},
{"learn":[0.2752101135],"iteration":785,"passed_time":4.881395803,"remaining_time":1.329031427},
{"learn":[0.2750541687],"iteration":786,"passed_time":4.889156905,"remaining_time":1.323240687},
{"learn":[0.2748062706],"iteration":787,"passed_time":4.893892624,"remaining_time":1.31663101},
{"learn":[0.2745674515],"iteration":788,"passed_time":4.897590802,"remaining_time":1.309748617},
{"learn":[0.2744745827],"iteration":789,"passed_time":4.905377269,"remaining_time":1.303961046},
{"learn":[0.2742120743],"iteration":790,"passed_time":4.908954971,"remaining_time":1.29705637},
{"learn":[0.2741307831],"iteration":791,"passed_time":4.912562098,"remaining_time":1.290167824},
{"learn":[0.2739676666],"iteration":792,"passed_time":4.918574821,"remaining_time":1.283915496},
{"learn":[0.2737384796],"iteration":793,"passed_time":4.923510424,"remaining_time":1.277384317},
{"learn":[0.2735991287],"iteration":794,"passed_time":4.927099415,"remaining_time":1.270509912},
{"learn":[0.2733948517],"iteration":795,"passed_time":4.930633157,"remaining_time":1.263629603},
{"learn":[0.2732143021],"iteration":796,"passed_time":4.937998178,"remaining_time":1.257733539},
{"learn":[0.2729663086],"iteration":797,"passed_time":4.94170876,"remaining_time":1.250908734},
{"learn":[0.2727468109],"iteration":798,"passed_time":4.945253197,"remaining_time":1.244049928},
{"learn":[0.2725085831],"iteration":799,"passed_time":4.952119559,"remaining_time":1.23802989},
{"learn":[0.2723018074],"iteration":800,"passed_time":4.955948804,"remaining_time":1.231253199},
{"learn":[0.2720883369],"iteration":801,"passed_time":4.959588956,"remaining_time":1.224437174},
{"learn":[0.2719146538],"iteration":802,"passed_time":4.965389447,"remaining_time":1.218159055},
{"learn":[0.2717323112],"iteration":803,"passed_time":4.971268424,"remaining_time":1.211901257},
{"learn":[0.2715839958],"iteration":804,"passed_time":4.975604419,"remaining_time":1.205270636},
{"learn":[0.2714523697],"iteration":805,"passed_time":4.987031947,"remaining_time":1.200352603},
{"learn":[0.271226387],"iteration":806,"passed_time":4.991574236,"remaining_time":1.193771781},
{"learn":[0.2709778595],"iteration":807,"passed_time":4.996624383,"remaining_time":1.187316685},
{"learn":[0.2706889153],"iteration":808,"passed_time":5.002144089,"remaining_time":1.180975922},
{"learn":[0.2705617142],"iteration":809,"passed_time":5.006251545,"remaining_time":1.174305918},
{"learn":[0.2703436089],"iteration":810,"passed_time":5.013375279,"remaining_time":1.168345164},
{"learn":[0.2699933815],"iteration":811,"passed_time":5.018110585,"remaining_time":1.161828559},
{"learn":[0.2697643089],"iteration":812,"passed_time":5.0216989,"remaining_time":1.155052515},
{"learn":[0.2696207619],"iteration":813,"passed_time":5.025550078,"remaining_time":1.148344367},
{"learn":[0.2693258858],"iteration":814,"passed_time":5.032888173,"remaining_time":1.142434739},
{"learn":[0.2690874863],"iteration":815,"passed_time":5.03639571,"remaining_time":1.135657856},
{"learn":[0.2689087105],"iteration":816,"passed_time":5.039936485,"remaining_time":1.128896422},
{"learn":[0.2687038231],"iteration":817,"passed_time":5.048017879,"remaining_time":1.123153122},
{"learn":[0.2684283257],"iteration":818,"passed_time":5.053058422,"remaining_time":1.116732081},
{"learn":[0.2683058167],"iteration":819,"passed_time":5.062399889,"remaining_time":1.111258512},
{"learn":[0.2680112839],"iteration":820,"passed_time":5.066760674,"remaining_time":1.104689599},
{"learn":[0.2679098511],"iteration":821,"passed_time":5.07093485,"remaining_time":1.098085649},
{"learn":[0.2676697922],"iteration":822,"passed_time":5.077945551,"remaining_time":1.092097646},
{"learn":[0.2673616791],"iteration":823,"passed_time":5.082876922,"remaining_time":1.085663032},
{"learn":[0.2671153259],"iteration":824,"passed_time":5.086967934,"remaining_time":1.079053804},
{"learn":[0.2667477608],"iteration":825,"passed_time":5.09352967,"remaining_time":1.072971141},
{"learn":[0.2666061974],"iteration":826,"passed_time":5.099405206,"remaining_time":1.066743774},
{"learn":[0.2663533592],"iteration":827,"passed_time":5.103869882,"remaining_time":1.060224178},
{"learn":[0.2661637688],"iteration":828,"passed_time":5.110849589,"remaining_time":1.054228323},
{"learn":[0.2661033058],"iteration":829,"passed_time":5.116911612,"remaining_time":1.048042137},
{"learn":[0.2659015656],"iteration":830,"passed_time":5.121427235,"remaining_time":1.04154176},
{"learn":[0.2657291412],"iteration":831,"passed_time":5.128636392,"remaining_time":1.035590041},
{"learn":[0.2655224228],"iteration":832,"passed_time":5.133011638,"remaining_time":1.029067159},
{"learn":[0.2654766083],"iteration":833,"passed_time":5.137352279,"remaining_time":1.02254254},
{"learn":[0.2653043365],"iteration":834,"passed_time":5.143839533,"remaining_time":1.016447333},
{"learn":[0.2652002335],"iteration":835,"passed_time":5.14824523,"remaining_time":1.009942844},
{"learn":[0.2649832535],"iteration":836,"passed_time":5.152688728,"remaining_time":1.003450732},
{"learn":[0.2647592735],"iteration":837,"passed_time":5.160003935,"remaining_time":0.9975186606},
{"learn":[0.2645595932],"iteration":838,"passed_time":5.164031077,"remaining_time":0.9909523282},
{"learn":[0.2643340683],"iteration":839,"passed_time":5.167608917,"remaining_time":0.9843064603},
{"learn":[0.2642235565],"iteration":840,"passed_time":5.17321509,"remaining_time":0.9780513667},
{"learn":[0.2640883446],"iteration":841,"passed_time":5.177487828,"remaining_time":0.9715475972},
{"learn":[0.2638459396],"iteration":842,"passed_time":5.18137292,"remaining_time":0.9649769259},
{"learn":[0.2636869431],"iteration":843,"passed_time":5.185389368,"remaining_time":0.9584368974},
{"learn":[0.2634179688],"iteration":844,"passed_time":5.193256069,"remaining_time":0.9526091015},
{"learn":[0.2632568741],"iteration":845,"passed_time":5.198738131,"remaining_time":0.9463424021},
{"learn":[0.2631171989],"iteration":846,"passed_time":5.204449283,"remaining_time":0.9401189377},
{"learn":[0.262924614],"iteration":847,"passed_time":5.208680099,"remaining_time":0.9336313385},
{"learn":[0.2627557373],"iteration":848,"passed_time":5.212269708,"remaining_time":0.9270350129},
{"learn":[0.2626764679],"iteration":849,"passed_time":5.215919965,"remaining_time":0.9204564644},
{"learn":[0.2625304794],"iteration":850,"passed_time":5.221850098,"remaining_time":0.9142839771},
{"learn":[0.2623945618],"iteration":851,"passed_time":5.225873674,"remaining_time":0.9077808729},
{"learn":[0.2623014832],"iteration":852,"passed_time":5.229466791,"remaining_time":0.9012094001},
{"learn":[0.2621503067],"iteration":853,"passed_time":5.233107989,"remaining_time":0.8946531222},
{"learn":[0.2620131302],"iteration":854,"passed_time":5.239126902,"remaining_time":0.8885069014},
{"learn":[0.2616579437],"iteration":855,"passed_time":5.243001886,"remaining_time":0.8820003172},
{"learn":[0.2615010071],"iteration":856,"passed_time":5.246628636,"remaining_time":0.8754584539},
{"learn":[0.261378479],"iteration":857,"passed_time":5.250591673,"remaining_time":0.8689790414},
{"learn":[0.2612830734],"iteration":858,"passed_time":5.25605546,"remaining_time":0.8627518275},
{"learn":[0.2611323547],"iteration":859,"passed_time":5.259619893,"remaining_time":0.856217192},
{"learn":[0.2610057068],"iteration":860,"passed_time":5.263222329,"remaining_time":0.8496955909},
{"learn":[0.2608652306],"iteration":861,"passed_time":5.26871165,"remaining_time":0.8434828395},
{"learn":[0.2606796265],"iteration":862,"passed_time":5.273041955,"remaining_time":0.8370877727},
{"learn":[0.2603890038],"iteration":863,"passed_time":5.27674013,"remaining_time":0.8305979834},
{"learn":[0.2602664566],"iteration":864,"passed_time":5.280263385,"remaining_time":0.8240873492},
{"learn":[0.2599840355],"iteration":865,"passed_time":5.286300829,"remaining_time":0.8179726456},
{"learn":[0.2598458862],"iteration":866,"passed_time":5.29154182,"remaining_time":0.8117359424},
{"learn":[0.2597187233],"iteration":867,"passed_time":5.29570053,"remaining_time":0.805336947},
{"learn":[0.2596251106],"iteration":868,"passed_time":5.302209736,"remaining_time":0.7992974401},
{"learn":[0.2594073105],"iteration":869,"passed_time":5.306595932,"remaining_time":0.792939622},
{"learn":[0.2592112923],"iteration":870,"passed_time":5.311040784,"remaining_time":0.7865950186},
{"learn":[0.2589676094],"iteration":871,"passed_time":5.317055624,"remaining_time":0.7804852293},
{"learn":[0.2587409592],"iteration":872,"passed_time":5.321340779,"remaining_time":0.7741240308},
{"learn":[0.258568821],"iteration":873,"passed_time":5.324943013,"remaining_time":0.76766913},
{"learn":[0.2584811783],"iteration":874,"passed_time":5.328371167,"remaining_time":0.761195881},
{"learn":[0.2582873917],"iteration":875,"passed_time":5.334016941,"remaining_time":0.7550434939},
{"learn":[0.2580932617],"iteration":876,"passed_time":5.337671376,"remaining_time":0.7486129751},
{"learn":[0.2579350853],"iteration":877,"passed_time":5.341147038,"remaining_time":0.7421639392},
{"learn":[0.257786026],"iteration":878,"passed_time":5.344624544,"remaining_time":0.7357219224},
{"learn":[0.257644577],"iteration":879,"passed_time":5.350885519,"remaining_time":0.7296662072},
{"learn":[0.2574569321],"iteration":880,"passed_time":5.354445482,"remaining_time":0.7232451899},
{"learn":[0.2573454666],"iteration":881,"passed_time":5.358019444,"remaining_time":0.7168325333},
{"learn":[0.2570828247],"iteration":882,"passed_time":5.361456811,"remaining_time":0.7104082072},
{"learn":[0.2569421768],"iteration":883,"passed_time":5.367541266,"remaining_time":0.7043379942},
{"learn":[0.256764698],"iteration":884,"passed_time":5.371259219,"remaining_time":0.6979602374},
{"learn":[0.2565948677],"iteration":885,"passed_time":5.374832355,"remaining_time":0.6915698516},
{"learn":[0.2565124893],"iteration":886,"passed_time":5.381434744,"remaining_time":0.6855717317},
{"learn":[0.2561318588],"iteration":887,"passed_time":5.388360014,"remaining_time":0.6796129748},
{"learn":[0.2559690285],"iteration":888,"passed_time":5.39239327,"remaining_time":0.6732909482},
{"learn":[0.2557436752],"iteration":889,"passed_time":5.399548882,"remaining_time":0.6673599742},
{"learn":[0.2555113602],"iteration":890,"passed_time":5.404149866,"remaining_time":0.6611137322},
{"learn":[0.2552998543],"iteration":891,"passed_time":5.407631273,"remaining_time":0.654735625},
{"learn":[0.2552105713],"iteration":892,"passed_time":5.412832669,"remaining_time":0.6485700958},
{"learn":[0.2550077629],"iteration":893,"passed_time":5.416703333,"remaining_time":0.642248941},
{"learn":[0.254899559],"iteration":894,"passed_time":5.420213181,"remaining_time":0.6358909318},
{"learn":[0.2546004486],"iteration":895,"passed_time":5.423691391,"remaining_time":0.6295356079},
{"learn":[0.2544695091],"iteration":896,"passed_time":5.428634331,"remaining_time":0.6233548897},
{"learn":[0.2542783737],"iteration":897,"passed_time":5.432272435,"remaining_time":0.6170287176},
{"learn":[0.2541251373],"iteration":898,"passed_time":5.437096088,"remaining_time":0.6108417185},
{"learn":[0.2539824677],"iteration":899,"passed_time":5.44069201,"remaining_time":0.6045213345},
{"learn":[0.2538877296],"iteration":900,"passed_time":5.446832189,"remaining_time":0.5984865557},
{"learn":[0.2537298584],"iteration":901,"passed_time":5.450491504,"remaining_time":0.5921820038},
{"learn":[0.2535693169],"iteration":902,"passed_time":5.453979119,"remaining_time":0.5858648666},
{"learn":[0.253300209],"iteration":903,"passed_time":5.457388439,"remaining_time":0.5795456749},
{"learn":[0.2530528641],"iteration":904,"passed_time":5.462711483,"remaining_time":0.5734338021},
{"learn":[0.2528581619],"iteration":905,"passed_time":5.466549449,"remaining_time":0.5671695897},
{"learn":[0.2527178383],"iteration":906,"passed_time":5.470735863,"remaining_time":0.5609464557},
{"learn":[0.2524829865],"iteration":907,"passed_time":5.47609234,"remaining_time":0.5548463604},
{"learn":[0.2524332619],"iteration":908,"passed_time":5.480148293,"remaining_time":0.5486177059},
{"learn":[0.2521361923],"iteration":909,"passed_time":5.484279239,"remaining_time":0.5424012434},
{"learn":[0.2519480133],"iteration":910,"passed_time":5.487818681,"remaining_time":0.5361315726},
{"learn":[0.2517803192],"iteration":911,"passed_time":5.493719944,"remaining_time":0.5300957841},
{"learn":[0.2515579033],"iteration":912,"passed_time":5.498345633,"remaining_time":0.5239387405},
{"learn":[0.251418438],"iteration":913,"passed_time":5.501783056,"remaining_time":0.5176732416},
{"learn":[0.2512144089],"iteration":914,"passed_time":5.505433374,"remaining_time":0.5114337014},
{"learn":[0.2510787582],"iteration":915,"passed_time":5.510690175,"remaining_time":0.505347134},
{"learn":[0.2507872009],"iteration":916,"passed_time":5.514229654,"remaining_time":0.4991069371},
{"learn":[0.2505909729],"iteration":917,"passed_time":5.517608661,"remaining_time":0.49285829},
{"learn":[0.2504555893],"iteration":918,"passed_time":5.521361493,"remaining_time":0.4866488367},
{"learn":[0.2503217697],"iteration":919,"passed_time":5.526314276,"remaining_time":0.4805490674},
{"learn":[0.2501998138],"iteration":920,"passed_time":5.529728552,"remaining_time":0.4743198215},
{"learn":[0.2500787926],"iteration":921,"passed_time":5.533212985,"remaining_time":0.4681026169},
{"learn":[0.2499270058],"iteration":922,"passed_time":5.536644997,"remaining_time":0.4618869608},
{"learn":[0.2497410393],"iteration":923,"passed_time":5.542708021,"remaining_time":0.4558937333},
{"learn":[0.2496201324],"iteration":924,"passed_time":5.546033334,"remaining_time":0.4496783784},
{"learn":[0.2495076561],"iteration":925,"passed_time":5.549471799,"remaining_time":0.4434783079},
{"learn":[0.2493762398],"iteration":926,"passed_time":5.553106888,"remaining_time":0.4372996794},
{"learn":[0.2492029381],"iteration":927,"passed_time":5.558335359,"remaining_time":0.4312501571},
{"learn":[0.2490122032],"iteration":928,"passed_time":5.562275669,"remaining_time":0.4251039532},
{"learn":[0.2489270782],"iteration":929,"passed_time":5.565677201,"remaining_time":0.4189219398},
{"learn":[0.2486915016],"iteration":930,"passed_time":5.570715011,"remaining_time":0.4128671705},
{"learn":[0.2485105515],"iteration":931,"passed_time":5.574527249,"remaining_time":0.4067251641},
{"learn":[0.2483107376],"iteration":932,"passed_time":5.578046836,"remaining_time":0.4005671361},
{"learn":[0.2481510353],"iteration":933,"passed_time":5.581411913,"remaining_time":0.3944038397},
{"learn":[0.2479552078],"iteration":934,"passed_time":5.586755993,"remaining_time":0.3883841065},
{"learn":[0.2478558922],"iteration":935,"passed_time":5.591034055,"remaining_time":0.3822929268},
{"learn":[0.2476015091],"iteration":936,"passed_time":5.594581307,"remaining_time":0.3761564806},
{"learn":[0.2473702049],"iteration":937,"passed_time":5.598053019,"remaining_time":0.370020562},
{"learn":[0.2471839333],"iteration":938,"passed_time":5.603252731,"remaining_time":0.3640025736},
{"learn":[0.2470514679],"iteration":939,"passed_time":5.607510857,"remaining_time":0.3579262249},
{"learn":[0.2468631744],"iteration":940,"passed_time":5.611479169,"remaining_time":0.3518355696},
{"learn":[0.2468005371],"iteration":941,"passed_time":5.614939449,"remaining_time":0.3457181402},
{"learn":[0.2466818047],"iteration":942,"passed_time":5.621053844,"remaining_time":0.3397667753},
{"learn":[0.2464419746],"iteration":943,"passed_time":5.624930211,"remaining_time":0.3336823007},
{"learn":[0.2463128662],"iteration":944,"passed_time":5.630525523,"remaining_time":0.3277025436},
{"learn":[0.2461025238],"iteration":945,"passed_time":5.635828134,"remaining_time":0.3217068914},
{"learn":[0.2459163857],"iteration":946,"passed_time":5.639371912,"remaining_time":0.3156142675},
{"learn":[0.2456811333],"iteration":947,"passed_time":5.642966036,"remaining_time":0.3095297826},
{"learn":[0.2455226135],"iteration":948,"passed_time":5.646740533,"remaining_time":0.3034602394},
{"learn":[0.2454672623],"iteration":949,"passed_time":5.652497829,"remaining_time":0.2974998857},
{"learn":[0.245370636],"iteration":950,"passed_time":5.656265978,"remaining_time":0.2914374689},
{"learn":[0.2451041222],"iteration":951,"passed_time":5.65984924,"remaining_time":0.2853705499},
{"learn":[0.2449121094],"iteration":952,"passed_time":5.663371552,"remaining_time":0.2793058373},
{"learn":[0.2447692299],"iteration":953,"passed_time":5.669373424,"remaining_time":0.2733660142},
{"learn":[0.2446127701],"iteration":954,"passed_time":5.672971276,"remaining_time":0.2673127826},
{"learn":[0.2444176865],"iteration":955,"passed_time":5.676413065,"remaining_time":0.2612575051},
{"learn":[0.2442848206],"iteration":956,"passed_time":5.679876342,"remaining_time":0.2552086549},
{"learn":[0.243991642],"iteration":957,"passed_time":5.686045864,"remaining_time":0.2492838479},
{"learn":[0.2438040352],"iteration":958,"passed_time":5.689516956,"remaining_time":0.2432431649},
{"learn":[0.243739872],"iteration":959,"passed_time":5.693004562,"remaining_time":0.2372085234},
{"learn":[0.2435972595],"iteration":960,"passed_time":5.696880814,"remaining_time":0.231194955},
{"learn":[0.2433773041],"iteration":961,"passed_time":5.702540898,"remaining_time":0.2252562933},
{"learn":[0.2430318832],"iteration":962,"passed_time":5.706895473,"remaining_time":0.2192680504},
{"learn":[0.2428199196],"iteration":963,"passed_time":5.710346935,"remaining_time":0.2132494706},
{"learn":[0.2427381134],"iteration":964,"passed_time":5.715777109,"remaining_time":0.2073079781},
{"learn":[0.2426448822],"iteration":965,"passed_time":5.719527893,"remaining_time":0.2013084352},
{"learn":[0.2425289154],"iteration":966,"passed_time":5.723173134,"remaining_time":0.1953099415},
{"learn":[0.2424017906],"iteration":967,"passed_time":5.726805638,"remaining_time":0.1893158889},
{"learn":[0.2422919464],"iteration":968,"passed_time":5.732919326,"remaining_time":0.1834060878},
{"learn":[0.2422410011],"iteration":969,"passed_time":5.736596407,"remaining_time":0.1774205074},
{"learn":[0.2419520569],"iteration":970,"passed_time":5.740417149,"remaining_time":0.1714439725},
{"learn":[0.2417738342],"iteration":971,"passed_time":5.744677507,"remaining_time":0.1654845372},
{"learn":[0.2416989899],"iteration":972,"passed_time":5.750086176,"remaining_time":0.1595604591},
{"learn":[0.241691246],"iteration":973,"passed_time":5.752655586,"remaining_time":0.1535616481},
{"learn":[0.241590004],"iteration":974,"passed_time":5.756201748,"remaining_time":0.1475949166},
{"learn":[0.2415452576],"iteration":975,"passed_time":5.759832547,"remaining_time":0.1416352266},
{"learn":[0.2412846756],"iteration":976,"passed_time":5.765596126,"remaining_time":0.1357305127},
{"learn":[0.2412201309],"iteration":977,"passed_time":5.769190751,"remaining_time":0.129777297},
{"learn":[0.2410528183],"iteration":978,"passed_time":5.772803866,"remaining_time":0.1238292964},
{"learn":[0.2408751488],"iteration":979,"passed_time":5.778017184,"remaining_time":0.1179187181},
{"learn":[0.2406282806],"iteration":980,"passed_time":5.782321161,"remaining_time":0.1119919491},
{"learn":[0.2404440308],"iteration":981,"passed_time":5.785960103,"remaining_time":0.1060562952},
{"learn":[0.240286293],"iteration":982,"passed_time":5.789500807,"remaining_time":0.1001236152},
{"learn":[0.2400596619],"iteration":983,"passed_time":5.795659925,"remaining_time":0.09423837277},
{"learn":[0.2399800491],"iteration":984,"passed_time":5.799418125,"remaining_time":0.08831601206},
{"learn":[0.2397455597],"iteration":985,"passed_time":5.803055533,"remaining_time":0.08239632603},
{"learn":[0.2396830559],"iteration":986,"passed_time":5.806550876,"remaining_time":0.0764793935},
{"learn":[0.2394766617],"iteration":987,"passed_time":5.813287442,"remaining_time":0.07060673006},
{"learn":[0.2393983459],"iteration":988,"passed_time":5.81799261,"remaining_time":0.06470972569},
{"learn":[0.2391714859],"iteration":989,"passed_time":5.821592481,"remaining_time":0.05880396445},
{"learn":[0.238911705],"iteration":990,"passed_time":5.828054217,"remaining_time":0.05292884758},
{"learn":[0.2387464523],"iteration":991,"passed_time":5.831845262,"remaining_time":0.04703101018},
{"learn":[0.2385889435],"iteration":992,"passed_time":5.835456173,"remaining_time":0.04113614623},
{"learn":[0.2384548569],"iteration":993,"passed_time":5.839381832,"remaining_time":0.03524777766},
{"learn":[0.2384329605],"iteration":994,"passed_time":5.845218721,"remaining_time":0.0293729584},
{"learn":[0.238247261],"iteration":995,"passed_time":5.848899866,"remaining_time":0.0234895577},
{"learn":[0.2381206894],"iteration":996,"passed_time":5.852619339,"remaining_time":0.01761069009},
{"learn":[0.2379753113],"iteration":997,"passed_time":5.857803464,"remaining_time":0.0117390851},
{"learn":[0.2378730392],"iteration":998,"passed_time":5.861619821,"remaining_time":0.005867487309},
{"learn":[0.2377358246],"iteration":999,"passed_time":5.865256411,"remaining_time":0}
]}